Workbook
Name DataType: 'Rules'!$I$2:$I$47
Name FAIR_Prinzipien: 'Rules'!$M$2:$M$47
Name IFC_Data_Type: 'Rules'!$J$2:$J$47
Name ISG___Informationssicherheitsgesetz: 'Rules'!$L$2:$L$47
Name Klassifikation: Rules!$B$2:$B$47
Name LifecycleStatus: 'Rules'!$N$2:$N$47
Name Markmals_Klassifikation: Rules!$F$2:$F$47
Name Objekt_Einordnung: 'Rules'!$A$2:$A$47
Name Property_Classification: 'Rules'!$E$2:$E$47
Name Status: 'Rules'!$K$2:$K$47
Name Klassen_Zuordnung: 'Rules'!$B$2:$B$47
Name Affectation_de_classe: 'Rules'!$C$2:$C$47
Name Assegnazione_della_classe: 'Rules'!$D$2:$D$47
Name Merkmals_Zuordnung: 'Rules'!$F$2:$F$47
Name Attribution_de_propriete: 'Rules'!$G$2:$G$47
Name Assegnazione_della_proprieta: 'Rules'!$H$2:$H$47

Sheet Impressum
B1: Strukturvorlage Handlungsempfehlung Data Dictionaries
B3: Dokumenteninformationen
C4: Status | D4: Entwurf
C5: Version | D5: v20260510
C6: Letzte Änderung | D6: 46152
C7: Autor | D7: Bauen digital Schweiz / buildingSMART Switzerland (BdCH/bSCH)
B9: Trägerschaft
B12: Mit freundlicher Unterstützung von
C13: Armasuisse | E13: Schweizerische Bundesbahnen (SBB AG)
C14: B+S AG | E14: Schweizerischer Baumeisterverband (SBV)
C15: Basler & Hofmann AG | D15: Lignum Holzwirtschaft Schweiz | E15: Schweizerischer Ingenieur- und Architektenverein (SIA)
C16: Baumschlager Eberle Zürich AG | D16: Lombardi AG | E16: Stadt Luzern
C17: Buildup AG | D17: Losinger Marazzi AG | E17: Stadt Zürich
C18: Bundesamt für Strassen (ASTRA) | D18: Marti Tunnel AG | E18: Steinmann Ingenieure und Planer AG
C19: CRB | D19: MEGA | E19: Suissetec
C20: Fachgruppe für Untertagbau (FGU) | D20: Mensch und Maschine Schweiz AG | E20: Swissgee
C21: FHNW | D21: Open BIM Verband | E21: SWKI / die Planer
C22: Frutiger AG | D22: Penzel Valier AG | E22: Terradata AG
C23: HKG | D23: Rhomberg Sersa Rail Group Schweiz | E23: Walo AG
C24: IBG Engineering AG | D24: Roundtable Gebäudetechnik
C25: ILF BERATENDE INGENIEURE AG | D25: Schindler Aufzüge AG
C26: Implenia Schweiz AG | D26: Siemens AG
B28: Abgrenzung | D28: Fokus auf Austauschformat IFC 4.3.2.0 (IFC4X3_ADD2)
D29: Andere Formate (z. B. CityGML, gbXML, LandXML) sind kein Bestandteil
D30: Keine Abbildung von Geodaten (Geologie, Topographie, Bewuchs, Gewässer)
D31: Strukturvorlage ist eine methodische Grundlage, kein vollständiger Datenkatalog
D32: Vollständige Datenkataloge müssen in Datenbanken realsiert werden
D33: Die Handlungsempfehlung ist keine Implementierungsrichtlinie für Softwareentwicklung
D34: Die Strukturvorlage ist ein Best Practice Beispiel und kann jederzeit an neue Anforderungen angepasst werden. Es wird davon abgeraten, auf der Basis der Strukturvorlage Applikationen oder Tools zu entwickeln.
D35: Keine konkrete Implementierung oder Vernetzung von Datenkatalogen
B38: Copyright
D41: https://creativecommons.org/licenses/by-nc-sa/4.0/
D49: mailto:info@bauen-digital.ch

Sheet Anleitung
A1: Anleitung Strukturvorlage Data Dictionaries
B3: Inhaltsverzeichnis
B5: 1 | C5: Handhabung
B6: 2 | C6: Governance
B7: 3 | C7: Objekte
B8: 4 | C8: Klassifikationen
B9: 5 | C9: Merkmale
B10: 6 | C10: Werteliste
B11: 7 | C11: Dokumente
B13: Hinweise zur Handhabung
D15: B | E15: C | F15: D | G15: E
B16: Hinweise zur Handhabung | C16: Erforderlich | D16: Erforderlich für Data Dictionary | E16: Sprachen | F16: Referenziert / System generiert | G16: Dropdown Liste
B17: A | C17: Erforderlich für Objektkatalog
C18: Definiert die Mindestandorderugen an einen Katalog. Unterscheidung zwischen ja = erforderlich / empfohlen / <leer> = nicht notwendig
B19: B | C19: Erforderlich für Data Dictionary
C20: Definiert die Mindestandorderugen an ein in einer Datenbank eingepfegtes Data Dictionaries. Unterscheidung zwischen ja = erforderlich / empfohlen / <leer> = nicht notwendig
B21: C | C21: Sprachen
C22: Angabe zur Sprache: mehrsprachig = muss in der für den Katalog führenden Sprache enthalten sein / EN, DE, FR, IT = gibt Sprache zwingend vor / Sprachneutral = nicht von Sprache abängig
B23: D | C23: Referenziert / System generiert
C24: Darf nicht vom Erstelle manuell ausgefüllt werden, sonern wird auf eine Quelle referenziert, resp. von eine Datenbank automatisch generiert
B25: E | C25: Dropdown Liste
C26: Verweist auf die Dropdownliste in diesem Template
A28: 2 | B28: Governance
B30: Vorgabe einer minimalen Governance für die verschiedenen Kataloge
B31: Optional können aller Regeln der SN EN ISO 23386 ergänzt werden
B33: A | C33: B | D33: C | E33: D | F33: E | G33: F | H33: G
B34: Governance | C34: Status | D34: Versionsdatum | E34: Herkunft (PROV) | F34: Regeln zur Festlegung von Merkmalen | G34: Regeln zur Festlegung von Merkmalsgruppen | H34: Management-Regeln für die Erstellung und Pflege
B35: B | C35: Vorgeschriebner Status des Merkmals während seines Lebenszyklus (Enumeration: active / inactive)
B36: C | C36: Datum der Version. Format nach ISO 8601 = YYYY-MM-DDThh:mm:ssTDZ (T = festes Trennzeichen zwischen Datum und Uhrzeit / TDZ = Zeitzonenbezeichnung. Z = UTC, Abweichung zu UTC angeben)
C38: EN: PROV = Provenance, DE = Herkunft, Entstehungsgeschichte oder Nachweis der Datenherkunft
C39: Um eindeutig, maschinenlesbar und für den Menschen verständlich zu sein, müssen Merkmale als Liste von Attributen festgelegt werden. Einige Attribute sind zwingend erforderlich und andere sind freigestellt.
C42: Um eindeutig, maschinenlesbar und für den Menschen verständlich zu sein, müssen Merkmalsgruppen als Liste von Attributen festgelegt werden. Einige Attribute sind zwingend erforderlich und andere sind freigestellt.
C45: Verbindliche Regeln zur Erstellung, Pflege und Versionierung von Merkmalen und Merkmaslgruppen sowie zur koordinierten Abstimmung und Freigabe zwischen Akteuren zur Sicherstellung von Qualität, Konsistenz und Interoperabilität.
B50: Objekte
C52: B | E52: D | F52: E | G52: F | H52: G | I52: H | J52: I | K52: J | L52: K | M52: L | N52: M | O52: N | P52: O | R52: Q | S52: R
B53: Strukturelle Einordnung | C53: Domäne | E53: Kategorie | F53: Objekte | G53: GUID/URI | H53: Objekt-ID | I53: Objekt-Einordnung | J53: Bezeichnung | K53: Designation | L53: Beschreibung | M53: Description | N53: IFC 4.3.2.0 (IFC4X3_ADD2) | O53: GUID/URI | P53: IfcObject Entity | R53: PredefinedType | S53: ObjectType
B55: Strukturelle Einordnung
C57: B | E57: D
B58: Strukturelle Einordnung | C58: Domäne | E58: Kategorie
C59: Fachlicher Gesamtbereich, oberste Gliederung nach Disziplin Biespiele: Architektur, Tragwerk, HVAC, Verkehrswegebau, Bahntechnik, Werkleitungen
B60: C | C60: Funktionale Einheit innerhalb einer Domäne. Bündelt Bauteile zu einer technischen Gesamtanlage oder Konstruktion. Beispiele: Lufttechnische Anlage, Fahrbahnkonstruktion, Oberbau Geleise, Abwasserentsorgung
B61: D | C61: Gliedert Komponenten nach technischer Funktion, Material oder Bauart. Beispiele: Verteilnetz Lüftung, Belagsschichten, Schwellen, Kanalisation
A63: 3.2 | B63: Objekte
B65: E | C65: F | D65: G | E65: H | F65: I | G65: J | H65: K | I65: L
B66: Objekte | C66: GUID/URI | D66: Objekt-ID | E66: Objekt-Einordnung | F66: Bezeichnung | G66: Designation | H66: Beschreibung | I66: Description
B67: F | C67: Global eindeutige, persistente Identifikatoren zur interoperablen Referenzierung von Ressourcen.
B68: G | C68: Stabiler, systeminterner Code zur eindeutigen, sprachneutralen Identifikation des Objekts. Mehrfach verwendete Objekte müssen die gleiche Objekt-ID besitzen
B69: H | C69: Einheitliche Einordnung von Objekten entlang einer strukturierten Gliederung (räumlich, logisch, kontextuell) als fachliche Abstraktion über den gesamten Lebenszyklus.
B70: I | C70: Eindeutiger, fachlicher Name eines Objekts zur Identifikation und Einordnung
B71: J | C71: EN: Unique, domain-specific name of an object for identification and classification
B72: K | C72: Kurzbeschreibung oder Definition zur fachlichen Erläuterung eines Objekts
B73: L | C73: EN: Short description or definition explaining an object in a domain context
A75: 3.3 | B75: IFC 4.3.2.0 (IFC4X3_ADD2)
B77: M | C77: N | D77: O | E77: P | F77: Q | G77: R
B78: IFC 4.3.2.0 (IFC4X3_ADD2) | C78: GUID/URI | D78: IfcObject Entity | E78: IfcTypeObject Entity | F78: PredefinedType | G78: ObjectType
B79: N | C79: Global eindeutige, persistente Identifikatoren zur interoperablen Referenzierung von Ressourcen.
B80: O | C80: Ein IfcObject ist die Verallgemeinerung jedes semantisch behandelten Objekts oder Prozesses. Objekte sind Dinge, wie sie erscheinen – d. h. Instanzen.
C81: Beispiele: physisch greifbare Elemente wie Wände, Träger oder Verkleidungen, physisch vorhandene Elemente wie Räume oder konzeptionelle Elemente wie Raster oder virtuelle Begrenzungen.
C82: Der Begriff steht auch für Prozesse wie Arbeitsaufgaben, für Steuerungselemente wie Kostenpositionen oder für Akteure wie Personen, die am Entwurfsprozess beteiligt sind.
B83: P | C83: Der Objekttyp definiert die spezifischen Informationen zu einem Typ, die allen Instanzen dieses Typs gemeinsam sind.
B84: Q | C84: Enumerierter Attributwert im IFC-Schema zur normierten Klassifizierung eines Objekttyps gemäss vordefinierter Auswahlliste.
B85: R | C85: Freitext-Attribut zur zusätzlichen, projektspezifischen Typisierung eines Objekts, wenn keine passende Klassifizierung über PredefinedType existiert.
A88: 4 | B88: Klassifikationen
B90: A | C90: B | D90: C | E90: D | F90: E | G90: F | H90: G | I90: H
C91: IfcClassification | G91: IfcClassRef
B92: Klassifikationen | C92: Specification | D92: Name | E92: Source | F92: Edition | G92: Location | H92: Identification | I92: Name
B93: B | C93: Ressourcenbezeichner oder -lokator der Klassifizierung, angegeben als URI, URN oder URL.
B94: C | C94: Die Bezeichnung oder das Kürzel, unter dem die verwendete Klassifikation üblicherweise bekannt ist.
B95: D | C95: Quelle (oder Herausgeber) der Klassifikation.
B96: E | C96: Die Ausgabe oder Version des Klassifizierungssystems, aus der die Klassifizierungsbezeichnung stammt.
B97: F | C97: Ort, an dem auf die externe Quelle (Klassifizierung, Dokument oder Bibliothek) auf elektronischem Wege zugegriffen werden kann. Der elektronische Speicherort wird als URI angegeben und normalerweise in Form einer URL-Adresse bereitgestellt.
B98: G | C98: Die Identifikation liefert eine eindeutige Kennung des referenzierten Elements innerhalb der externen Quelle (Klassifikation, Dokument oder Bibliothek). Sie kann in Form von * einem Schlüssel, z. B. einer Klassifikationsbezeichnung wie NF2.3, einer UUID oder einer GUID vorliegen
B99: H | C99: Optionaler Name zur genaueren Spezifizierung der Referenz. Er kann als für Menschen lesbare Kennung dienen (die nicht unbedingt eine Entsprechung in der internen Struktur des Dokuments haben muss).
A101: 5 | B101: Merkmale
C103: Merkmale | M103: IFC 4.3.2.0 | R103: MG
B104: A | C104: B | D104: C | E104: D | F104: E | G104: F | H104: G | I104: H | J104: I | K104: J | L104: K | M104: L | N104: M | O104: N | P104: O | Q104: P | R104: Q
B105: Merkmale | C105: GUID/URI | D105: Merkmal-ID | E105: Merkmal | F105: Property | G105: Beschreibung | H105: Description (EN) | I105: DataType (Base Type) | J105: DataType (IFC) | K105: Werteliste-ID | L105: IFC 4.3.2.0 (IFC4X3_ADD2) | M105: GUID/URI | N105: IfcPropertySet (Pset) | O105: IfcQuantitySet (Qto) | P105: Benutzerdefiniertes PropertySet | Q105: Merkmalsgruppen | R105: Merkmalsgruppe (group of property)
A107: 5.1 | B107: Merkmale
B109: A | C109: B | D109: C | E109: D | F109: E | G109: F | H109: G | I109: H | J109: I | K109: J
B110: Merkmal | C110: GUID/URI | D110: Merkmal-ID | E110: Merkmal | F110: Property | G110: Beschreibung | H110: Description (EN) | I110: DataType (Base Type) | J110: DataType (IFC) | K110: Werteliste-ID
B111: B | C111: Global eindeutige, persistente Identifikatoren zur interoperablen Referenzierung von Ressourcen.
B112: C | C112: Stabiler, systeminterner Code zur eindeutigen, sprachneutralen Identifikation des Objekts. Mehrfach verwendete Objekte müssen die gleiche Objekt-ID besitzen
B113: D | C113: Fachlich definiertes Attribut zur strukturierten Beschreibung eines Objekts in einem Datenkatalog.
B114: E | C114: EN: Defined attribute used to describe an object in a structured and machine-readable way.
B115: F | C115: Textliche Erläuterung zur fachlichen Bedeutung und Anwendung eines Merkmals.
B116: G | C116: EN: Textual explanation of the meaning and intended use of a property.
B117: H | C117: Grundlegender Datentyp (z. B. STRING, REAL) zur Festlegung von Struktur und Werteformat. Hinweis: Entspricht PA030 - Attribute eines Merkmals
B118: I | C118: IFC-spezifischer Datentyp (z. B. IfcLabel, IfcReal) gemäss ISO 16739-1 zur Standardisierung.
B119: J | C119: Stabiler, systeminterner Code zur eindeutigen, sprachneutralen Identifikation der Werteliste.
A121: 5.2 | B121: IFC 4.3.2.0 (IFC4X3_ADD2)
B123: K | C123: L | D123: M | E123: N | F123: O
B124: IFC 4.3.2.0 (IFC4X3_ADD2) | C124: GUID/URI | D124: IfcPropertySet (Pset) | E124: IfcQuantitySet (Qto) | F124: Benutzerdefiniertes PropertySet
B125: L | C125: Global eindeutige, persistente Identifikatoren zur interoperablen Referenzierung von Ressourcen.
C126: Hinweis: Entspricht PA001 - Attribute eines Merkmals
B127: M | C127: Beschreibt eine Liste von Merkmalen für eine IFC-Entität. Merkmalssätze, deren Struktur und Eigenschaften fest in der IFC-Spezifikation definiert sind (z. B. Pset_WallCommon oder Pset_DoorCommon).
B128: N | C128: Beschreibt eine Liste von Mengen für eine IFC-Entität. Mengen­sätze, deren Struktur und Inhalte in der IFC-Spezifikation definiert sind (z. B. Qto_WallBaseQuantities).
B129: O | C129: Beschreibt eine Liste von Merkmalen für eine IFC-Entität. Dient dazu, projekt-, regionalspezifische oder anwendungsspezifische Merkmale zu erfassen, die nicht standardmässig in der IFC-Spezifikation enthalten sind.
A131: 5.3 | B131: Merkmalsgruppen
B133: P | C133: Q
B134: Merkmalsgruppen | C134: Merkmalsgruppe (group of property)
...

Sheet Header
A1: Data Dictionary — Core Metadata
A2: Field | B2: Value | C2: Requirement | D2: Notes / Maps to
A3: IDENTIFICATION
A4: OrganizationCode | B4: KBOB | C4: user defined name (small or capital letters), max 7 chars | D4: Short org code — lowercase, max 7 chars, appears in all derived IRIs
A5: DictionaryCode | B5: kbob_fm_data_dictionary | C5: SYSTEM-GENERATED | D5: Generated from DictionaryName (EN)
A6: DictionaryName (EN) | B6: KBOB FM Data Dictionary | C6: REQUIRED | D6: Required authoring title in English — source for DictionaryCode generation
A7: DictionaryName (DE) | B7: KBOB Datenkatalog FM | C7: OPTIONAL | D7: Core authoring title in German — minimal DCAT/i14y anchor
A8: DictionaryName (FR) | B8: Catalogue de données KBOB FM | C8: OPTIONAL | D8: Optional multilingual title support
A9: DictionaryName (IT)
A10: DictionaryVersion | B10: 0.3.0 | C10: REQUIRED | D10: Semantic versioning: MAJOR.MINOR.PATCH
A11: DictionaryUri | B11: https://lindas.admin.ch/KBOB/kbob_fm_data_dictionary | C11: SYSTEM-GENERATED | D11: Derived from OrganizationCode and DictionaryCode; canonical base pattern https://example.com/<OrganizationCode>/<DictionaryCode>
A13: GOVERNANCE
A14: LifecycleStatus | B14: Candidate | C14: REQUIRED | D14: Governance state used to derive i14y registration status
A16: LEGEND
A17: REQUIRED: | B17: Must be filled before validation/export
A18: OPTIONAL: | B18: Fill if available

Sheet Dictionary_public
A1: Data Dictionary — Additional Metadata
A2: Field | B2: Value | C2: Requirement | D2: Notes / Maps to
A3: GOVERNANCE / PUBLISHING
A4: Owner / Publisher | C4: REQUIRED WHEN USED | D4: dct:publisher / i14y publisher mapping
A5: ContactEmail | C5: REQUIRED WHEN USED | D5: dcat:contactPoint / i14y contact
A6: Description (DE) | C6: REQUIRED WHEN USED | D6: dct:description@de
A7: Description (FR) | C7: OPTIONAL | D7: dct:description@fr
A8: Description (EN) | C8: OPTIONAL | D8: dct:description@en
A9: PrimaryLanguage | C9: REQUIRED WHEN USED | D9: Primary metadata/content language
A10: MetadataLanguages | C10: OPTIONAL | D10: Additional metadata languages; delimited list allowed
A11: ReleaseDate | C11: OPTIONAL | D11: dct:issued — format YYYY-MM-DD
A12: ModifiedDate | C12: OPTIONAL
A13: QualityAssuranceProcedure | C13: OPTIONAL
A14: QualityAssuranceProcedureUrl | C14: OPTIONAL
A16: DISCOVERY / CATALOG METADATA
A17: Keywords (DE) | C17: OPTIONAL | D17: German keywords/tags — dcat:keyword@de
A18: Keywords (FR) | C18: OPTIONAL | D18: French keywords/tags — dcat:keyword@fr
A19: Keywords (EN) | C19: OPTIONAL | D19: English keywords/tags — dcat:keyword@en
A20: AccessRights | C20: OPTIONAL | D20: Access rights / visibility statement — dct:accessRights
A21: eCH_Theme | C21: OPTIONAL | D21: Swiss eCH thematic classification / topic category
A22: SpatialCoverage | C22: OPTIONAL | D22: Geographic scope or covered territory — dct:spatial
A23: TemporalCoverage | C23: OPTIONAL | D23: Covered time period / validity period — dct:temporal
A24: DocumentationURLs | C24: OPTIONAL | D24: Supporting documentation links; delimited list allowed
A25: RelatedResourceURLs | C25: OPTIONAL | D25: Related datasets/resources links — dct:relation
A26: ApplicableLegislation | C26: OPTIONAL | D26: Applicable legal basis / legislation references
A28: LICENSING
A29: License | C29: OPTIONAL | D29: Human-readable license name — dct:license
A30: LicenseUrl | C30: OPTIONAL | D30: Resolvable license URI/URL — dct:license
A32: TECHNICAL ENDPOINTS
A33: SPARQL_Endpoint | C33: OPTIONAL | D33: SPARQL endpoint URL for published graph access
A34: TTL_Download_URL | C34: OPTIONAL | D34: Download URL for Turtle/RDF serialization — dcat:distribution
A35: JSON_Download_URL | C35: OPTIONAL | D35: Download URL for JSON/JSON-LD serialization — dcat:distribution
A36: MoreInfoUrl | C36: OPTIONAL | D36: Landing page / homepage
A38: STANDARDS ALIGNMENT
A39: ConformsTo_ISO23386 | C39: OPTIONAL | D39: dct:conformsTo — property methodology
A40: ConformsTo_ISO12006_3 | C40: OPTIONAL
A41: ConformsTo_DCAT_AP_CH | C41: OPTIONAL
A42: VersionNotes (DE) | C42: OPTIONAL
A43: VersionNotes (FR) | C43: OPTIONAL
A44: VersionNotes (EN) | C44: OPTIONAL

Sheet Classes
A1: Filter | B1: Hinweise zur Handhabung | C1: Structural categorisation | D1: Domain/Domäne/Domaine/Dominio | E1: System/System/Système/Sistema | F1: Category/Kategorie/Catégorie/Categoria | G1: Classes | H1: GUID/URI | I1: Class-ID | J1: Class-Code | K1: Class-Assignment | L1: Klassen-Zuordnung (DE) | M1: Affectation de classe (FR) | N1: Assegnazione della classe (IT) | O1: Designation (EN) | P1: Bezeichnung (DE) | Q1: Désignation (FR) | R1: Designazione (IT) | S1: Description (EN) | T1: Beschreibung (DE) | U1: Description (FR) | V1: Descrizione (IT) | W1: IFC 4.3.2.0 (IFC4X3_ADD2) | X1: IFC_URI | Y1: IfcObject Entity | Z1: IfcTypeObject Entity | AA1: PredefinedType | AB1: ObjectType | AC1: RDS | AD1: Governance | AE1: Status | AF1: Version date | AG1: Provenance (PROV) | AH1: RelatedDocuments | AI1: RelatedDocumentName (EN)
B2: Erforderlich für Excel
B3: Sprachen
B4: Referenziert / System generiert | D4: multilingual | E4: multilingual | F4: multilingual | H4: multilingual | I4: multilingual | J4: multilingual | K4: multilingual | L4: DE | M4: FR | N4: IT | O4: EN | P4: DE | Q4: FR | R4: IT | S4: EN | T4: DE | U4: FR | V4: IT | X4: multilingual | Y4: multilingual | Z4: multilingual | AA4: multilingual | AB4: multilingual | AC4: multilingual | AE4: multilingual | AF4: multilingual | AG4: multilingual | AI4: multilingual
B5: Dropdown Liste | H5: referenced | I5: system-generated | L5: system-generated | M5: system-generated | N5: system-generated | X5: referenced | Y5: referenced | Z5: referenced | AA5: referenced | AB5: referenced | AC5: referenced | AE5: referenced | AF5: referenced | AG5: referenced | AI5: referenced
B6: Validierung | K6: Rules.Class-Assignment | L6: Rules.Klassen-Zuordnung | M6: Rules.Affectation de classe | N6: Rules.Assegnazione della classe | AE6: Rules.Status
H7: https://www.kbob.admin.ch/class/grundstuck | I7: site | J7: grundstuck | K7: Spatial structure | L7: Räumliche Struktur | M7: Structure spatiale | N7: Struttura spaziale | O7: Site | P7: Grundstück | S7: KBOB FM object class for a site as a spatial unit of a developed or undeveloped plot. | T7: KBOB-FM-Objektklasse für ein Grundstück als räumliche Einheit des bebauten oder unbebauten Areals. | X7: https://identifier.buildingsmart.org/uri/buildingsmart/ifc/4.3/class/IfcSite | Y7: IfcSite | Z7: IfcSite | AE7: Candidate | AF7: 2026-06-30T12:00:00Z | AG7: KBOB | AI7: KBOB DK FM_i14y.csv
H8: https://www.kbob.admin.ch/class/gebaude | I8: building | J8: gebaude | K8: Spatial structure | L8: Räumliche Struktur | M8: Structure spatiale | N8: Struttura spaziale | O8: Building | P8: Gebäude | S8: KBOB FM object class for a building as an independent built asset. | T8: KBOB-FM-Objektklasse für ein Gebäude als eigenständiges Bauwerk. | X8: https://identifier.buildingsmart.org/uri/buildingsmart/ifc/4.3/class/IfcBuilding | Y8: IfcBuilding | Z8: IfcBuilding | AE8: Candidate | AF8: 2026-06-30T12:00:00Z | AG8: KBOB | AI8: KBOB DK FM_i14y.csv
H9: https://www.kbob.admin.ch/class/geschoss | I9: storey | J9: geschoss | K9: Spatial structure | L9: Räumliche Struktur | M9: Structure spatiale | N9: Struttura spaziale | O9: Storey | P9: Geschoss | S9: KBOB FM object class for a storey as a spatial level within a building. | T9: KBOB-FM-Objektklasse für ein Geschoss als räumliche Ebene innerhalb eines Gebäudes. | X9: https://identifier.buildingsmart.org/uri/buildingsmart/ifc/4.3/class/IfcBuildingStorey | Y9: IfcBuildingStorey | Z9: IfcBuildingStorey | AE9: Candidate | AF9: 2026-06-30T12:00:00Z | AG9: KBOB | AI9: KBOB DK FM_i14y.csv
H10: https://www.kbob.admin.ch/class/raum | I10: room | J10: raum | K10: Spatial structure | L10: Räumliche Struktur | M10: Structure spatiale | N10: Struttura spaziale | O10: Room | P10: Raum | S10: KBOB FM object class for a room as a usable spatial unit within a storey. | T10: KBOB-FM-Objektklasse für einen Raum als nutzbare räumliche Einheit innerhalb eines Geschosses. | X10: https://identifier.buildingsmart.org/uri/buildingsmart/ifc/4.3/class/IfcSpace | Y10: IfcSpace | Z10: IfcSpace | AE10: Candidate | AF10: 2026-06-30T12:00:00Z | AG10: KBOB | AI10: KBOB DK FM_i14y.csv
H11: https://www.kbob.admin.ch/class/bauteil | I11: component | J11: bauteil | K11: Physical elements | L11: Physische Bauteile | M11: Éléments physiques | N11: Elementi fisici | O11: Component | P11: Bauteil | S11: KBOB FM object class for a component as an identifiable element of a building or facility. | T11: KBOB-FM-Objektklasse für ein Bauteil als identifizierbares Element eines Bauwerks oder einer Anlage. | X11: https://identifier.buildingsmart.org/uri/buildingsmart/ifc/4.3/class/IfcElement | Y11: IfcElement | Z11: IfcElement | AE11: Candidate | AF11: 2026-06-30T12:00:00Z | AG11: KBOB | AI11: KBOB DK FM_i14y.csv
L12: =IFERROR(INDEX(Rules!$B:$B,MATCH(K13,Rules!$A:$A,0)),"") | M12: =IFERROR(INDEX(Rules!$C:$C,MATCH(K13,Rules!$A:$A,0)),"") | N12: =IFERROR(INDEX(Rules!$D:$D,MATCH(K13,Rules!$A:$A,0)),"")
L13: =IFERROR(INDEX(Rules!$B:$B,MATCH(K14,Rules!$A:$A,0)),"") | M13: =IFERROR(INDEX(Rules!$C:$C,MATCH(K14,Rules!$A:$A,0)),"") | N13: =IFERROR(INDEX(Rules!$D:$D,MATCH(K14,Rules!$A:$A,0)),"")
L14: =IFERROR(INDEX(Rules!$B:$B,MATCH(K15,Rules!$A:$A,0)),"") | M14: =IFERROR(INDEX(Rules!$C:$C,MATCH(K15,Rules!$A:$A,0)),"") | N14: =IFERROR(INDEX(Rules!$D:$D,MATCH(K15,Rules!$A:$A,0)),"")
L15: =IFERROR(INDEX(Rules!$B:$B,MATCH(K16,Rules!$A:$A,0)),"") | M15: =IFERROR(INDEX(Rules!$C:$C,MATCH(K16,Rules!$A:$A,0)),"") | N15: =IFERROR(INDEX(Rules!$D:$D,MATCH(K16,Rules!$A:$A,0)),"")
L16: =IFERROR(INDEX(Rules!$B:$B,MATCH(K17,Rules!$A:$A,0)),"") | M16: =IFERROR(INDEX(Rules!$C:$C,MATCH(K17,Rules!$A:$A,0)),"") | N16: =IFERROR(INDEX(Rules!$D:$D,MATCH(K17,Rules!$A:$A,0)),"")
L17: =IFERROR(INDEX(Rules!$B:$B,MATCH(K18,Rules!$A:$A,0)),"") | M17: =IFERROR(INDEX(Rules!$C:$C,MATCH(K18,Rules!$A:$A,0)),"") | N17: =IFERROR(INDEX(Rules!$D:$D,MATCH(K18,Rules!$A:$A,0)),"")
L18: =IFERROR(INDEX(Rules!$B:$B,MATCH(K19,Rules!$A:$A,0)),"") | M18: =IFERROR(INDEX(Rules!$C:$C,MATCH(K19,Rules!$A:$A,0)),"") | N18: =IFERROR(INDEX(Rules!$D:$D,MATCH(K19,Rules!$A:$A,0)),"")
L19: =IFERROR(INDEX(Rules!$B:$B,MATCH(K20,Rules!$A:$A,0)),"") | M19: =IFERROR(INDEX(Rules!$C:$C,MATCH(K20,Rules!$A:$A,0)),"") | N19: =IFERROR(INDEX(Rules!$D:$D,MATCH(K20,Rules!$A:$A,0)),"")
L20: =IFERROR(INDEX(Rules!$B:$B,MATCH(K21,Rules!$A:$A,0)),"") | M20: =IFERROR(INDEX(Rules!$C:$C,MATCH(K21,Rules!$A:$A,0)),"") | N20: =IFERROR(INDEX(Rules!$D:$D,MATCH(K21,Rules!$A:$A,0)),"")
L21: =IFERROR(INDEX(Rules!$B:$B,MATCH(K22,Rules!$A:$A,0)),"") | M21: =IFERROR(INDEX(Rules!$C:$C,MATCH(K22,Rules!$A:$A,0)),"") | N21: =IFERROR(INDEX(Rules!$D:$D,MATCH(K22,Rules!$A:$A,0)),"")
L22: =IFERROR(INDEX(Rules!$B:$B,MATCH(K23,Rules!$A:$A,0)),"") | M22: =IFERROR(INDEX(Rules!$C:$C,MATCH(K23,Rules!$A:$A,0)),"") | N22: =IFERROR(INDEX(Rules!$D:$D,MATCH(K23,Rules!$A:$A,0)),"")
L23: =IFERROR(INDEX(Rules!$B:$B,MATCH(K24,Rules!$A:$A,0)),"") | M23: =IFERROR(INDEX(Rules!$C:$C,MATCH(K24,Rules!$A:$A,0)),"") | N23: =IFERROR(INDEX(Rules!$D:$D,MATCH(K24,Rules!$A:$A,0)),"")
L24: =IFERROR(INDEX(Rules!$B:$B,MATCH(K25,Rules!$A:$A,0)),"") | M24: =IFERROR(INDEX(Rules!$C:$C,MATCH(K25,Rules!$A:$A,0)),"") | N24: =IFERROR(INDEX(Rules!$D:$D,MATCH(K25,Rules!$A:$A,0)),"")

Sheet Properties
A1: Filter | B1: Hinweise zur Handhabung | C1: Properties | D1: GUID/URI | E1: Property-ID | F1: Property-Code | G1: Property-Assignment | H1: Merkmals-Zuordnung (DE) | I1: Attribution de propriété (FR) | J1: Assegnazione della proprietà (IT) | K1: Designation (EN) | L1: Bezeichnung (DE) | M1: Désignation (FR) | N1: Designazione (IT) | O1: Description (EN) | P1: Beschreibung (DE) | Q1: Description (FR) | R1: Descrizione (IT) | S1: DataType (Base Type) | T1: DataType (IFC) | U1: EnumerationDesignation (EN) | V1: IFC 4.3.2.0 (IFC4X3_ADD2) | W1: IFC_URI | X1: IfcPropertySet (Pset) IfcQuantitySet (Qto) | Y1: Units/Einheit/Unité/Unità | Z1: QUDT URI | AA1: Unit Name (EN) | AB1: Einheit-Name (DE) | AC1: Nom de l’unité (FR) | AD1: Nome unità (IT) | AE1: Governance | AF1: Status | AG1: Version date | AH1: Provenance (PROV)
B2: Erforderlich für Excel | G2: yes
B3: Sprachen
B4: Referenziert / System generiert | D4: multilingual | E4: multilingual | F4: multilingual | H4: DE | I4: FR | J4: IT | K4: EN | L4: DE | M4: FR | N4: IT | O4: EN | P4: DE | Q4: FR | R4: IT | S4: multilingual | T4: multilingual | U4: multilingual | W4: multilingual | X4: multilingual | Y4: multilingual | Z4: multilingual | AA4: EN | AB4: DE | AC4: FR | AD4: IT | AF4: multilingual | AG4: multilingual | AH4: multilingual
B5: Dropdown Liste | D5: referenced | E5: system-generated | H5: system-generated | I5: system-generated | J5: system-generated | S5: referenced | T5: referenced | U5: referenced | W5: referenced | X5: referenced | Z5: referenced | AA5: system-generated | AB5: system-generated | AC5: system-generated | AD5: system-generated | AF5: referenced | AG5: referenced | AH5: referenced
B6: Validierung | G6: Rules.Property-Assignment | H6: Rules.Merkmals-Zuordnung | I6: Rules.Attribution de propriété | J6: Rules.Assegnazione della proprietà | S6: Rules.DataType | T6: Rules.IFC Data Type | AF6: Rules.Status
E7: guid | F7: guid | H7: =IFERROR(INDEX(Rules!$F:$F,MATCH(G8,Rules!$E:$E,0)),"") | I7: =IFERROR(INDEX(Rules!$G:$G,MATCH(G8,Rules!$E:$E,0)),"") | J7: =IFERROR(INDEX(Rules!$H:$H,MATCH(G8,Rules!$E:$E,0)),"") | K7: GUID | L7: GUID | O7: Property for uniquely identifying the object by means of a global unique identifier (GUID). | P7: Merkmal zur eindeutigen Identifikation des Objekts mittels Global Unique Identifier (GUID). | S7: STRING | T7: IfcLabel | W7: https://identifier.buildingsmart.org/uri/buildingsmart/ifc/4.3/prop/GlobalId | AF7: Candidate | AG7: 2026-06-30T12:00:00Z | AH7: KBOB
E8: site-id | F8: grundstuck-id | H8: =IFERROR(INDEX(Rules!$F:$F,MATCH(G9,Rules!$E:$E,0)),"") | I8: =IFERROR(INDEX(Rules!$G:$G,MATCH(G9,Rules!$E:$E,0)),"") | J8: =IFERROR(INDEX(Rules!$H:$H,MATCH(G9,Rules!$E:$E,0)),"") | K8: Site ID | L8: Grundstück ID | O8: Property for uniquely identifying sites. | P8: Merkmal zur eindeutigen Identifikation von Grundstücken. | S8: STRING | T8: IfcLabel | W8: https://identifier.buildingsmart.org/uri/buildingsmart/ifc/4.3/prop/LandID | X8: https://identifier.buildingsmart.org/uri/buildingsmart/ifc/4.3/class/Pset_LandRegistration | AF8: Candidate | AG8: 2026-06-30T12:00:00Z | AH8: KBOB
E9: economic-unit-id | F9: wirtschaftseinheit-id | H9: =IFERROR(INDEX(Rules!$F:$F,MATCH(G10,Rules!$E:$E,0)),"") | I9: =IFERROR(INDEX(Rules!$G:$G,MATCH(G10,Rules!$E:$E,0)),"") | J9: =IFERROR(INDEX(Rules!$H:$H,MATCH(G10,Rules!$E:$E,0)),"") | K9: Economic unit ID | L9: Wirtschaftseinheit ID | O9: Property for uniquely identifying economic units. | P9: Merkmal zur eindeutigen Identifikation von Wirtschaftseinheiten. | S9: STRING | T9: IfcLabel | W9: https://identifier.buildingsmart.org/uri/buildingsmart/ifc/4.3/prop/LandTitleID | X9: https://identifier.buildingsmart.org/uri/buildingsmart/ifc/4.3/class/Pset_LandRegistration | AF9: Candidate | AG9: 2026-06-30T12:00:00Z | AH9: KBOB
E10: location | F10: ort | H10: =IFERROR(INDEX(Rules!$F:$F,MATCH(G11,Rules!$E:$E,0)),"") | I10: =IFERROR(INDEX(Rules!$G:$G,MATCH(G11,Rules!$E:$E,0)),"") | J10: =IFERROR(INDEX(Rules!$H:$H,MATCH(G11,Rules!$E:$E,0)),"") | K10: Location | L10: Ort | O10: Property for specifying the location. | P10: Merkmal zur Angabe von dem Ort. | S10: STRING | T10: IfcLabel | W10: https://identifier.buildingsmart.org/uri/buildingsmart/ifc/4.3/prop/Town | X10: https://identifier.buildingsmart.org/uri/buildingsmart/ifc/4.3/class/Pset_Address | AF10: Candidate | AG10: 2026-06-30T12:00:00Z | AH10: KBOB
E11: designation | F11: bezeichnung | H11: =IFERROR(INDEX(Rules!$F:$F,MATCH(G12,Rules!$E:$E,0)),"") | I11: =IFERROR(INDEX(Rules!$G:$G,MATCH(G12,Rules!$E:$E,0)),"") | J11: =IFERROR(INDEX(Rules!$H:$H,MATCH(G12,Rules!$E:$E,0)),"") | K11: Designation | L11: Bezeichnung | O11: Property for specifying the designation. | P11: Merkmal zur Angabe von der Bezeichnung. | S11: STRING | T11: IfcLabel | W11: https://identifier.buildingsmart.org/uri/buildingsmart/ifc/4.3/prop/Name | AF11: Candidate | AG11: 2026-06-30T12:00:00Z | AH11: KBOB
E12: country-code | F12: landeskurzel | H12: =IFERROR(INDEX(Rules!$F:$F,MATCH(G13,Rules!$E:$E,0)),"") | I12: =IFERROR(INDEX(Rules!$G:$G,MATCH(G13,Rules!$E:$E,0)),"") | J12: =IFERROR(INDEX(Rules!$H:$H,MATCH(G13,Rules!$E:$E,0)),"") | K12: Country code | L12: Landeskürzel | O12: Property for specifying the country code. | P12: Merkmal zur Angabe von dem Landeskürzel. | S12: STRING | T12: IfcLabel | W12: https://identifier.buildingsmart.org/uri/buildingsmart/ifc/4.3/prop/Country | X12: https://identifier.buildingsmart.org/uri/buildingsmart/ifc/4.3/class/Pset_Address | AF12: Candidate | AG12: 2026-06-30T12:00:00Z | AH12: KBOB
E13: canton | F13: kanton | H13: =IFERROR(INDEX(Rules!$F:$F,MATCH(G14,Rules!$E:$E,0)),"") | I13: =IFERROR(INDEX(Rules!$G:$G,MATCH(G14,Rules!$E:$E,0)),"") | J13: =IFERROR(INDEX(Rules!$H:$H,MATCH(G14,Rules!$E:$E,0)),"") | K13: Canton | L13: Kanton | O13: Property for specifying the canton. | P13: Merkmal zur Angabe von dem Kanton. | S13: STRING | T13: IfcLabel | W13: https://identifier.buildingsmart.org/uri/buildingsmart/ifc/4.3/prop/Region | X13: https://identifier.buildingsmart.org/uri/buildingsmart/ifc/4.3/class/Pset_Address | AF13: Candidate | AG13: 2026-06-30T12:00:00Z | AH13: KBOB
E14: postal-code | F14: postleitzahl | H14: =IFERROR(INDEX(Rules!$F:$F,MATCH(G15,Rules!$E:$E,0)),"") | I14: =IFERROR(INDEX(Rules!$G:$G,MATCH(G15,Rules!$E:$E,0)),"") | J14: =IFERROR(INDEX(Rules!$H:$H,MATCH(G15,Rules!$E:$E,0)),"") | K14: Postal code | L14: Postleitzahl | O14: Property for specifying the postal code. | P14: Merkmal zur Angabe von der Postleitzahl. | S14: INTEGER | T14: IfcLabel | W14: https://identifier.buildingsmart.org/uri/buildingsmart/ifc/4.3/prop/PostalCode | X14: https://identifier.buildingsmart.org/uri/buildingsmart/ifc/4.3/class/Pset_Address | AF14: Candidate | AG14: 2026-06-30T12:00:00Z | AH14: KBOB
E15: political-municipality | F15: politische-gemeinde | H15: =IFERROR(INDEX(Rules!$F:$F,MATCH(G16,Rules!$E:$E,0)),"") | I15: =IFERROR(INDEX(Rules!$G:$G,MATCH(G16,Rules!$E:$E,0)),"") | J15: =IFERROR(INDEX(Rules!$H:$H,MATCH(G16,Rules!$E:$E,0)),"") | K15: Political municipality | L15: Politische Gemeinde | O15: Property for specifying the political municipality. | P15: Merkmal zur Angabe von der politischen Gemeinde. | S15: STRING | T15: IfcLabel | W15: https://identifier.buildingsmart.org/uri/buildingsmart/ifc/4.3/prop/Town | X15: https://identifier.buildingsmart.org/uri/buildingsmart/ifc/4.3/class/Pset_Address | AF15: Candidate | AG15: 2026-06-30T12:00:00Z | AH15: KBOB
E16: gis-parcel-number | F16: gis-parzellennummer | H16: =IFERROR(INDEX(Rules!$F:$F,MATCH(G17,Rules!$E:$E,0)),"") | I16: =IFERROR(INDEX(Rules!$G:$G,MATCH(G17,Rules!$E:$E,0)),"") | J16: =IFERROR(INDEX(Rules!$H:$H,MATCH(G17,Rules!$E:$E,0)),"") | K16: GIS parcel number | L16: GIS-Parzellennummer | O16: Property for specifying the GIS parcel number. | P16: Merkmal zur Angabe von der GIS-Parzellennummer. | S16: STRING | T16: IfcLabel | W16: https://identifier.buildingsmart.org/uri/buildingsmart/ifc/4.3/prop/LandID | X16: https://identifier.buildingsmart.org/uri/buildingsmart/ifc/4.3/class/Pset_LandRegistration | AF16: Candidate | AG16: 2026-06-30T12:00:00Z | AH16: KBOB
E17: site-area | F17: grundstucksflache | H17: =IFERROR(INDEX(Rules!$F:$F,MATCH(G18,Rules!$E:$E,0)),"") | I17: =IFERROR(INDEX(Rules!$G:$G,MATCH(G18,Rules!$E:$E,0)),"") | J17: =IFERROR(INDEX(Rules!$H:$H,MATCH(G18,Rules!$E:$E,0)),"") | K17: Site area | L17: Grundstücksfläche | O17: Property for specifying the site area. | P17: Merkmal zur Angabe der Grundstücksfläche. | S17: REAL | T17: IfcAreaMeasure | W17: https://identifier.buildingsmart.org/uri/buildingsmart/ifc/4.3/prop/GrossArea | X17: https://identifier.buildingsmart.org/uri/buildingsmart/ifc/4.3/class/Qto_SiteBaseQuantities | Y17: m² | Z17: http://qudt.org/vocab/unit/M2 | AA17: square meter | AB17: quadratmeter | AC17: mètre carré | AD17: metro quadrato | AF17: Candidate | AG17: 2026-06-30T12:00:00Z | AH17: KBOB
E18: owner-entity | F18: eigentumerin | H18: =IFERROR(INDEX(Rules!$F:$F,MATCH(G19,Rules!$E:$E,0)),"") | I18: =IFERROR(INDEX(Rules!$G:$G,MATCH(G19,Rules!$E:$E,0)),"") | J18: =IFERROR(INDEX(Rules!$H:$H,MATCH(G19,Rules!$E:$E,0)),"") | K18: Owner entity | L18: Eigentümerin | O18: Property for specifying the owner. | P18: Merkmal zur Angabe von der Eigentümerin. | S18: STRING | T18: IfcLabel | AF18: Candidate | AG18: 2026-06-30T12:00:00Z | AH18: KBOB
E19: easement-id | F19: dienstbarkeiten-id | H19: =IFERROR(INDEX(Rules!$F:$F,MATCH(G20,Rules!$E:$E,0)),"") | I19: =IFERROR(INDEX(Rules!$G:$G,MATCH(G20,Rules!$E:$E,0)),"") | J19: =IFERROR(INDEX(Rules!$H:$H,MATCH(G20,Rules!$E:$E,0)),"") | K19: Easement ID | L19: Dienstbarkeiten ID | O19: Property for uniquely identifying easements. | P19: Merkmal zur eindeutigen Identifikation von Dienstbarkeiten. | S19: STRING | T19: IfcLabel | W19: https://identifier.buildingsmart.org/uri/buildingsmart/ifc/4.3/prop/LandTitleID | X19: https://identifier.buildingsmart.org/uri/buildingsmart/ifc/4.3/class/Pset_LandRegistration | AF19: Candidate | AG19: 2026-06-30T12:00:00Z | AH19: KBOB
E20: easement-name | F20: dienstbarkeitenname | H20: =IFERROR(INDEX(Rules!$F:$F,MATCH(G21,Rules!$E:$E,0)),"") | I20: =IFERROR(INDEX(Rules!$G:$G,MATCH(G21,Rules!$E:$E,0)),"") | J20: =IFERROR(INDEX(Rules!$H:$H,MATCH(G21,Rules!$E:$E,0)),"") | K20: Easement name | L20: Dienstbarkeitenname | O20: Property for specifying the easement name. | P20: Merkmal zur Angabe von dem Namen der Dienstbarkeit. | S20: STRING | T20: IfcLabel | W20: https://identifier.buildingsmart.org/uri/buildingsmart/ifc/4.3/prop/LandTitleID | X20: https://identifier.buildingsmart.org/uri/buildingsmart/ifc/4.3/class/Pset_LandRegistration | AF20: Candidate | AG20: 2026-06-30T12:00:00Z | AH20: KBOB
E21: building-id | F21: gebaude-id | H21: =IFERROR(INDEX(Rules!$F:$F,MATCH(G22,Rules!$E:$E,0)),"") | I21: =IFERROR(INDEX(Rules!$G:$G,MATCH(G22,Rules!$E:$E,0)),"") | J21: =IFERROR(INDEX(Rules!$H:$H,MATCH(G22,Rules!$E:$E,0)),"") | K21: Building ID | L21: Gebäude ID | O21: Property for uniquely identifying buildings. | P21: Merkmal zur eindeutigen Identifikation von Gebäuden. | S21: STRING | T21: IfcLabel | W21: https://identifier.buildingsmart.org/uri/buildingsmart/ifc/4.3/prop/BuildingID | X21: https://identifier.buildingsmart.org/uri/buildingsmart/ifc/4.3/class/Pset_BuildingCommon | AF21: Candidate | AG21: 2026-06-30T12:00:00Z | AH21: KBOB
E22: object-id | F22: objekt-id | H22: =IFERROR(INDEX(Rules!$F:$F,MATCH(G23,Rules!$E:$E,0)),"") | I22: =IFERROR(INDEX(Rules!$G:$G,MATCH(G23,Rules!$E:$E,0)),"") | J22: =IFERROR(INDEX(Rules!$H:$H,MATCH(G23,Rules!$E:$E,0)),"") | K22: Object ID | L22: Objekt ID | O22: Property for uniquely identifying objects. | P22: Merkmal zur eindeutigen Identifikation von Objekten. | S22: STRING | T22: IfcLabel | W22: https://identifier.buildingsmart.org/uri/buildingsmart/ifc/4.3/prop/BuildingID | X22: https://identifier.buildingsmart.org/uri/buildingsmart/ifc/4.3/class/Pset_BuildingCommon | AF22: Candidate | AG22: 2026-06-30T12:00:00Z | AH22: KBOB
E23: building-designation | F23: gebaudebezeichnung | H23: =IFERROR(INDEX(Rules!$F:$F,MATCH(G24,Rules!$E:$E,0)),"") | I23: =IFERROR(INDEX(Rules!$G:$G,MATCH(G24,Rules!$E:$E,0)),"") | J23: =IFERROR(INDEX(Rules!$H:$H,MATCH(G24,Rules!$E:$E,0)),"") | K23: Building designation | L23: Gebäudebezeichnung | O23: Property for specifying the building designation. | P23: Merkmal zur Angabe von der Gebäudebezeichnung. | S23: STRING | T23: IfcLabel | W23: https://identifier.buildingsmart.org/uri/buildingsmart/ifc/4.3/prop/Name | AF23: Candidate | AG23: 2026-06-30T12:00:00Z | AH23: KBOB
E24: object-type | F24: objekttyp | H24: =IFERROR(INDEX(Rules!$F:$F,MATCH(G25,Rules!$E:$E,0)),"") | I24: =IFERROR(INDEX(Rules!$G:$G,MATCH(G25,Rules!$E:$E,0)),"") | J24: =IFERROR(INDEX(Rules!$H:$H,MATCH(G25,Rules!$E:$E,0)),"") | K24: Object type | L24: Objekttyp | O24: Property for specifying the object type. | P24: Merkmal zur Angabe von dem Objekttyp. | S24: STRING | T24: IfcLabel | W24: https://identifier.buildingsmart.org/uri/buildingsmart/ifc/4.3/prop/ObjectType | AF24: Candidate | AG24: 2026-06-30T12:00:00Z | AH24: KBOB
E25: street-and-house-number | F25: strasse-hausnummer | H25: =IFERROR(INDEX(Rules!$F:$F,MATCH(G26,Rules!$E:$E,0)),"") | I25: =IFERROR(INDEX(Rules!$G:$G,MATCH(G26,Rules!$E:$E,0)),"") | J25: =IFERROR(INDEX(Rules!$H:$H,MATCH(G26,Rules!$E:$E,0)),"") | K25: Street and house number | L25: Strasse Hausnummer | O25: Property for specifying the street and house number. | P25: Merkmal zur Angabe von Strasse und Hausnummer. | S25: STRING | T25: IfcLabel | W25: https://identifier.buildingsmart.org/uri/buildingsmart/ifc/4.3/prop/AddressLines | X25: https://identifier.buildingsmart.org/uri/buildingsmart/ifc/4.3/class/Pset_Address | AF25: Candidate | AG25: 2026-06-30T12:00:00Z | AH25: KBOB
E26: project-references | F26: projektreferenzen | H26: =IFERROR(INDEX(Rules!$F:$F,MATCH(G27,Rules!$E:$E,0)),"") | I26: =IFERROR(INDEX(Rules!$G:$G,MATCH(G27,Rules!$E:$E,0)),"") | J26: =IFERROR(INDEX(Rules!$H:$H,MATCH(G27,Rules!$E:$E,0)),"") | K26: Project references | L26: Projektreferenzen | O26: Property for specifying project references. | P26: Merkmal zur Angabe von den Projektreferenzen. | S26: STRING | T26: IfcLabel | W26: https://identifier.buildingsmart.org/uri/buildingsmart/ifc/4.3/prop/ModelReference | X26: https://identifier.buildingsmart.org/uri/buildingsmart/ifc/4.3/class/Pset_ManufacturerTypeInformation | AF26: Candidate | AG26: 2026-06-30T12:00:00Z | AH26: KBOB
E27: hazard-level | F27: gefahrdungsstufe | H27: =IFERROR(INDEX(Rules!$F:$F,MATCH(G28,Rules!$E:$E,0)),"") | I27: =IFERROR(INDEX(Rules!$G:$G,MATCH(G28,Rules!$E:$E,0)),"") | J27: =IFERROR(INDEX(Rules!$H:$H,MATCH(G28,Rules!$E:$E,0)),"") | K27: Hazard level | L27: Gefährdungsstufe | O27: Property for specifying the hazard level. | P27: Merkmal zur Angabe von der Gefährdungsstufe. | S27: STRING | T27: IfcLabel | W27: https://identifier.buildingsmart.org/uri/buildingsmart/ifc/4.3/prop/RiskType | X27: https://identifier.buildingsmart.org/uri/buildingsmart/ifc/4.3/class/Pset_Risk | AF27: Candidate | AG27: 2026-06-30T12:00:00Z | AH27: KBOB
E28: cost-centre | F28: kostentrager | H28: =IFERROR(INDEX(Rules!$F:$F,MATCH(G29,Rules!$E:$E,0)),"") | I28: =IFERROR(INDEX(Rules!$G:$G,MATCH(G29,Rules!$E:$E,0)),"") | J28: =IFERROR(INDEX(Rules!$H:$H,MATCH(G29,Rules!$E:$E,0)),"") | K28: Cost centre | L28: Kostenträger | O28: Property for specifying the cost centre. | P28: Merkmal zur Angabe von dem Kostenträger. | S28: STRING | T28: IfcLabel | AF28: Candidate | AG28: 2026-06-30T12:00:00Z | AH28: KBOB
E29: object-manager | F29: objektverantwortlicher | H29: =IFERROR(INDEX(Rules!$F:$F,MATCH(G30,Rules!$E:$E,0)),"") | I29: =IFERROR(INDEX(Rules!$G:$G,MATCH(G30,Rules!$E:$E,0)),"") | J29: =IFERROR(INDEX(Rules!$H:$H,MATCH(G30,Rules!$E:$E,0)),"") | K29: Object manager | L29: Objektverantwortlicher | O29: Property for specifying the object manager. | P29: Merkmal zur Angabe von dem Objektverantwortlichen. | S29: STRING | T29: IfcLabel | AF29: Candidate | AG29: 2026-06-30T12:00:00Z | AH29: KBOB
E30: building-footprint-area | F30: gebaudegrundflache | H30: =IFERROR(INDEX(Rules!$F:$F,MATCH(G31,Rules!$E:$E,0)),"") | I30: =IFERROR(INDEX(Rules!$G:$G,MATCH(G31,Rules!$E:$E,0)),"") | J30: =IFERROR(INDEX(Rules!$H:$H,MATCH(G31,Rules!$E:$E,0)),"") | K30: Building footprint area | L30: Gebäudegrundfläche | O30: Property for specifying the building footprint area. | P30: Merkmal zur Angabe der Gebäudegrundfläche. | S30: REAL | T30: IfcAreaMeasure | W30: https://identifier.buildingsmart.org/uri/buildingsmart/ifc/4.3/prop/GrossFloorArea | X30: https://identifier.buildingsmart.org/uri/buildingsmart/ifc/4.3/class/Qto_BuildingBaseQuantities | Y30: m² | Z30: http://qudt.org/vocab/unit/M2 | AA30: square meter | AB30: quadratmeter | AC30: mètre carré | AD30: metro quadrato | AF30: Candidate | AG30: 2026-06-30T12:00:00Z | AH30: KBOB
E31: building-volume | F31: gebaudevolumen | H31: =IFERROR(INDEX(Rules!$F:$F,MATCH(G32,Rules!$E:$E,0)),"") | I31: =IFERROR(INDEX(Rules!$G:$G,MATCH(G32,Rules!$E:$E,0)),"") | J31: =IFERROR(INDEX(Rules!$H:$H,MATCH(G32,Rules!$E:$E,0)),"") | K31: Building volume | L31: Gebäudevolumen | O31: Property for specifying the the building volume. | P31: Merkmal zur Angabe der dem Gebäudevolumen. | S31: REAL | T31: IfcReal | W31: https://identifier.buildingsmart.org/uri/buildingsmart/ifc/4.3/prop/GrossVolume | X31: https://identifier.buildingsmart.org/uri/buildingsmart/ifc/4.3/class/Qto_BodyGeometryValidation | Y31: m³ | Z31: http://qudt.org/vocab/unit/M3 | AA31: cubic meter | AB31: kubikmeter | AC31: mètre cube | AD31: metro cubo | AF31: Candidate | AG31: 2026-06-30T12:00:00Z | AH31: KBOB
E32: building-insurance-number | F32: nummer-gebaudeversicherung | H32: =IFERROR(INDEX(Rules!$F:$F,MATCH(G33,Rules!$E:$E,0)),"") | I32: =IFERROR(INDEX(Rules!$G:$G,MATCH(G33,Rules!$E:$E,0)),"") | J32: =IFERROR(INDEX(Rules!$H:$H,MATCH(G33,Rules!$E:$E,0)),"") | K32: Building insurance number | L32: Nummer Gebäudeversicherung | O32: Property for specifying the building insurance number. | P32: Merkmal zur Angabe von der Nummer der Gebäudeversicherung. | S32: STRING | T32: IfcLabel | W32: https://identifier.buildingsmart.org/uri/buildingsmart/ifc/4.3/prop/AssetInsuranceType | X32: https://identifier.buildingsmart.org/uri/buildingsmart/ifc/4.3/class/Pset_Asset | AF32: Candidate | AG32: 2026-06-30T12:00:00Z | AH32: KBOB
E33: year-of-construction | F33: baujahr | H33: =IFERROR(INDEX(Rules!$F:$F,MATCH(G34,Rules!$E:$E,0)),"") | I33: =IFERROR(INDEX(Rules!$G:$G,MATCH(G34,Rules!$E:$E,0)),"") | J33: =IFERROR(INDEX(Rules!$H:$H,MATCH(G34,Rules!$E:$E,0)),"") | K33: Year of construction | L33: Baujahr | O33: Property for specifying the year of construction. | P33: Merkmal zur Angabe von dem Baujahr. | S33: INTEGER | T33: IfcLabel | W33: https://identifier.buildingsmart.org/uri/buildingsmart/ifc/4.3/prop/YearOfConstruction | X33: https://identifier.buildingsmart.org/uri/buildingsmart/ifc/4.3/class/Pset_BuildingCommon | AF33: Candidate | AG33: 2026-06-30T12:00:00Z | AH33: KBOB
E34: owner | F34: eigentumer | H34: =IFERROR(INDEX(Rules!$F:$F,MATCH(G35,Rules!$E:$E,0)),"") | I34: =IFERROR(INDEX(Rules!$G:$G,MATCH(G35,Rules!$E:$E,0)),"") | J34: =IFERROR(INDEX(Rules!$H:$H,MATCH(G35,Rules!$E:$E,0)),"") | K34: Owner | L34: Eigentümer | O34: Property for specifying the owner. | P34: Merkmal zur Angabe von dem Eigentümer. | S34: STRING | T34: IfcLabel | AF34: Candidate | AG34: 2026-06-30T12:00:00Z | AH34: KBOB
E35: electrical-utility-connection | F35: medienbezug-elektrisch | H35: =IFERROR(INDEX(Rules!$F:$F,MATCH(G36,Rules!$E:$E,0)),"") | I35: =IFERROR(INDEX(Rules!$G:$G,MATCH(G36,Rules!$E:$E,0)),"") | J35: =IFERROR(INDEX(Rules!$H:$H,MATCH(G36,Rules!$E:$E,0)),"") | K35: Electrical utility connection | L35: Medienbezug Elektrisch | O35: Property for specifying the electrical utility connection. | P35: Merkmal zur Angabe von dem elektrischen Medienbezug. | S35: STRING | T35: IfcLabel | W35: https://identifier.buildingsmart.org/uri/buildingsmart/ifc/4.3/prop/Electricity | X35: https://identifier.buildingsmart.org/uri/buildingsmart/ifc/4.3/class/Pset_UtilityConsumptionPHistory | AF35: Candidate | AG35: 2026-06-30T12:00:00Z | AH35: KBOB
E36: water-utility-connection | F36: medienbezug-wasser | H36: =IFERROR(INDEX(Rules!$F:$F,MATCH(G37,Rules!$E:$E,0)),"") | I36: =IFERROR(INDEX(Rules!$G:$G,MATCH(G37,Rules!$E:$E,0)),"") | J36: =IFERROR(INDEX(Rules!$H:$H,MATCH(G37,Rules!$E:$E,0)),"") | K36: Water utility connection | L36: Medienbezug Wasser | O36: Property for specifying the water utility connection. | P36: Merkmal zur Angabe von dem Wasserbezug. | S36: STRING | T36: IfcLabel | W36: https://identifier.buildingsmart.org/uri/buildingsmart/ifc/4.3/prop/WaterConsumption | X36: https://identifier.buildingsmart.org/uri/buildingsmart/ifc/4.3/class/Pset_EnvironmentalImpactValues | AF36: Candidate | AG36: 2026-06-30T12:00:00Z | AH36: KBOB
E37: heating-utility-connection | F37: medienbezug-heizung | H37: =IFERROR(INDEX(Rules!$F:$F,MATCH(G38,Rules!$E:$E,0)),"") | I37: =IFERROR(INDEX(Rules!$G:$G,MATCH(G38,Rules!$E:$E,0)),"") | J37: =IFERROR(INDEX(Rules!$H:$H,MATCH(G38,Rules!$E:$E,0)),"") | K37: Heating utility connection | L37: Medienbezug Heizung | O37: Property for specifying the heating utility connection. | P37: Merkmal zur Angabe von dem Heizungsbezug. | S37: STRING | T37: IfcLabel | W37: https://identifier.buildingsmart.org/uri/buildingsmart/ifc/4.3/prop/HeatingDesignAirFlow | X37: https://identifier.buildingsmart.org/uri/buildingsmart/ifc/4.3/class/Pset_SpaceAirHandlingDimensioning | AF37: Candidate | AG37: 2026-06-30T12:00:00Z | AH37: KBOB
E38: outdoor-use-type | F38: nutzungsart-aussen | H38: =IFERROR(INDEX(Rules!$F:$F,MATCH(G39,Rules!$E:$E,0)),"") | I38: =IFERROR(INDEX(Rules!$G:$G,MATCH(G39,Rules!$E:$E,0)),"") | J38: =IFERROR(INDEX(Rules!$H:$H,MATCH(G39,Rules!$E:$E,0)),"") | K38: Outdoor use type | L38: Nutzungsart aussen | O38: Property for specifying the outdoor use type. | P38: Merkmal zur Angabe von der Nutzungsart im Aussenbereich. | S38: STRING | T38: IfcLabel | W38: https://identifier.buildingsmart.org/uri/buildingsmart/ifc/4.3/prop/MarketCategory | X38: https://identifier.buildingsmart.org/uri/buildingsmart/ifc/4.3/class/Pset_BuildingUse | AF38: Candidate | AG38: 2026-06-30T12:00:00Z | AH38: KBOB
E39: building-class | F39: gebaudeklasse | H39: =IFERROR(INDEX(Rules!$F:$F,MATCH(G40,Rules!$E:$E,0)),"") | I39: =IFERROR(INDEX(Rules!$G:$G,MATCH(G40,Rules!$E:$E,0)),"") | J39: =IFERROR(INDEX(Rules!$H:$H,MATCH(G40,Rules!$E:$E,0)),"") | K39: Building class | L39: Gebäudeklasse | O39: Property for specifying the building class. | P39: Merkmal zur Angabe von der Gebäudeklasse. | S39: STRING | T39: IfcLabel | W39: https://identifier.buildingsmart.org/uri/buildingsmart/ifc/4.3/prop/OccupancyType | X39: https://identifier.buildingsmart.org/uri/buildingsmart/ifc/4.3/class/Pset_SpaceOccupancyRequirements | AF39: Candidate | AG39: 2026-06-30T12:00:00Z | AH39: KBOB
E40: building-label | F40: gebaudelabel | H40: =IFERROR(INDEX(Rules!$F:$F,MATCH(G41,Rules!$E:$E,0)),"") | I40: =IFERROR(INDEX(Rules!$G:$G,MATCH(G41,Rules!$E:$E,0)),"") | J40: =IFERROR(INDEX(Rules!$H:$H,MATCH(G41,Rules!$E:$E,0)),"") | K40: Building label | L40: Gebäudelabel | O40: Property for specifying the building label. | P40: Merkmal zur Angabe von dem Gebäudelabel. | S40: STRING | T40: IfcLabel | W40: https://identifier.buildingsmart.org/uri/buildingsmart/ifc/4.3/prop/ModelLabel | X40: https://identifier.buildingsmart.org/uri/buildingsmart/ifc/4.3/class/Pset_ManufacturerTypeInformation | AF40: Candidate | AG40: 2026-06-30T12:00:00Z | AH40: KBOB
E41: sustainability-certification | F41: nachhaltigkeitsnachweis | H41: =IFERROR(INDEX(Rules!$F:$F,MATCH(G42,Rules!$E:$E,0)),"") | I41: =IFERROR(INDEX(Rules!$G:$G,MATCH(G42,Rules!$E:$E,0)),"") | J41: =IFERROR(INDEX(Rules!$H:$H,MATCH(G42,Rules!$E:$E,0)),"") | K41: Sustainability certification | L41: Nachhaltigkeitsnachweis | O41: Property for specifying the sustainability certification. | P41: Merkmal zur Angabe von dem Nachhaltigkeitsnachweis. | S41: STRING | T41: IfcLabel | AF41: Candidate | AG41: 2026-06-30T12:00:00Z | AH41: KBOB
E42: heritage-status | F42: denkmalstatus | H42: =IFERROR(INDEX(Rules!$F:$F,MATCH(G43,Rules!$E:$E,0)),"") | I42: =IFERROR(INDEX(Rules!$G:$G,MATCH(G43,Rules!$E:$E,0)),"") | J42: =IFERROR(INDEX(Rules!$H:$H,MATCH(G43,Rules!$E:$E,0)),"") | K42: Heritage status | L42: Denkmalstatus | O42: Property for specifying the heritage status. | P42: Merkmal zur Angabe von dem Denkmalstatus. | S42: STRING | T42: IfcLabel | W42: https://identifier.buildingsmart.org/uri/buildingsmart/ifc/4.3/prop/IsLandmarked | X42: https://identifier.buildingsmart.org/uri/buildingsmart/ifc/4.3/class/Pset_BuildingCommon | AF42: Candidate | AG42: 2026-06-30T12:00:00Z | AH42: KBOB
E43: seismic-building-class | F43: erdbebenbauwerksklasse | H43: =IFERROR(INDEX(Rules!$F:$F,MATCH(G44,Rules!$E:$E,0)),"") | I43: =IFERROR(INDEX(Rules!$G:$G,MATCH(G44,Rules!$E:$E,0)),"") | J43: =IFERROR(INDEX(Rules!$H:$H,MATCH(G44,Rules!$E:$E,0)),"") | K43: Seismic building class | L43: Erdbebenbauwerksklasse | O43: Property for specifying the seismic building class. | P43: Merkmal zur Angabe von der Erdbebenbauwerksklasse. | S43: STRING | T43: IfcLabel | W43: https://identifier.buildingsmart.org/uri/buildingsmart/ifc/4.3/prop/SeismicResistance | X43: https://identifier.buildingsmart.org/uri/buildingsmart/ifc/4.3/class/Pset_EnvironmentalCondition | AF43: Candidate | AG43: 2026-06-30T12:00:00Z | AH43: KBOB
E44: protection-zone | F44: schutzzone | H44: =IFERROR(INDEX(Rules!$F:$F,MATCH(G45,Rules!$E:$E,0)),"") | I44: =IFERROR(INDEX(Rules!$G:$G,MATCH(G45,Rules!$E:$E,0)),"") | J44: =IFERROR(INDEX(Rules!$H:$H,MATCH(G45,Rules!$E:$E,0)),"") | K44: Protection zone | L44: Schutzzone | O44: Property for specifying the protection zone. | P44: Merkmal zur Angabe von der Schutzzone. | S44: STRING | T44: IfcLabel | AF44: Candidate | AG44: 2026-06-30T12:00:00Z | AH44: KBOB
E45: surrounding-area-id | F45: umgebungsflache-id | H45: =IFERROR(INDEX(Rules!$F:$F,MATCH(G46,Rules!$E:$E,0)),"") | I45: =IFERROR(INDEX(Rules!$G:$G,MATCH(G46,Rules!$E:$E,0)),"") | J45: =IFERROR(INDEX(Rules!$H:$H,MATCH(G46,Rules!$E:$E,0)),"") | K45: Surrounding area ID | L45: Umgebungsfläche ID | O45: Property for uniquely identifying surrounding areas. | P45: Merkmal zur eindeutigen Identifikation von Umgebungsflächen. | S45: STRING | T45: IfcLabel | W45: https://identifier.buildingsmart.org/uri/buildingsmart/ifc/4.3/prop/LandID | X45: https://identifier.buildingsmart.org/uri/buildingsmart/ifc/4.3/class/Pset_LandRegistration | AF45: Candidate | AG45: 2026-06-30T12:00:00Z | AH45: KBOB
E46: surrounding-area-number | F46: umgebungsflachennummer | H46: =IFERROR(INDEX(Rules!$F:$F,MATCH(G47,Rules!$E:$E,0)),"") | I46: =IFERROR(INDEX(Rules!$G:$G,MATCH(G47,Rules!$E:$E,0)),"") | J46: =IFERROR(INDEX(Rules!$H:$H,MATCH(G47,Rules!$E:$E,0)),"") | K46: Surrounding area number | L46: Umgebungsflächennummer | O46: Property for specifying the surrounding area number. | P46: Merkmal zur Angabe von der Umgebungsflächennummer. | S46: STRING | T46: IfcLabel | W46: https://identifier.buildingsmart.org/uri/buildingsmart/ifc/4.3/prop/LandID | X46: https://identifier.buildingsmart.org/uri/buildingsmart/ifc/4.3/class/Pset_LandRegistration | AF46: Candidate | AG46: 2026-06-30T12:00:00Z | AH46: KBOB
E47: storey-id | F47: geschoss-id | H47: =IFERROR(INDEX(Rules!$F:$F,MATCH(G48,Rules!$E:$E,0)),"") | I47: =IFERROR(INDEX(Rules!$G:$G,MATCH(G48,Rules!$E:$E,0)),"") | J47: =IFERROR(INDEX(Rules!$H:$H,MATCH(G48,Rules!$E:$E,0)),"") | K47: Storey ID | L47: Geschoss ID | O47: Property for uniquely identifying storeys. | P47: Merkmal zur eindeutigen Identifikation von Geschossen. | S47: STRING | T47: IfcLabel | AF47: Candidate | AG47: 2026-06-30T12:00:00Z | AH47: KBOB
E48: storey-designation | F48: geschossbezeichnung | H48: =IFERROR(INDEX(Rules!$F:$F,MATCH(G49,Rules!$E:$E,0)),"") | I48: =IFERROR(INDEX(Rules!$G:$G,MATCH(G49,Rules!$E:$E,0)),"") | J48: =IFERROR(INDEX(Rules!$H:$H,MATCH(G49,Rules!$E:$E,0)),"") | K48: Storey designation | L48: Geschossbezeichnung | O48: Property for specifying the storey designation. | P48: Merkmal zur Angabe von der Geschossbezeichnung. | S48: STRING | T48: IfcLabel | W48: https://identifier.buildingsmart.org/uri/buildingsmart/ifc/4.3/prop/Name | AF48: Candidate | AG48: 2026-06-30T12:00:00Z | AH48: KBOB
E49: storey-volume | F49: geschossvolumen | H49: =IFERROR(INDEX(Rules!$F:$F,MATCH(G50,Rules!$E:$E,0)),"") | I49: =IFERROR(INDEX(Rules!$G:$G,MATCH(G50,Rules!$E:$E,0)),"") | J49: =IFERROR(INDEX(Rules!$H:$H,MATCH(G50,Rules!$E:$E,0)),"") | K49: Storey volume | L49: Geschossvolumen | O49: Property for specifying the the storey volume. | P49: Merkmal zur Angabe der dem Geschossvolumen. | S49: REAL | T49: IfcVolumeMeasure | W49: https://identifier.buildingsmart.org/uri/buildingsmart/ifc/4.3/prop/GrossVolume | X49: https://identifier.buildingsmart.org/uri/buildingsmart/ifc/4.3/class/Qto_BodyGeometryValidation | Y49: m³ | Z49: http://qudt.org/vocab/unit/M3 | AA49: cubic meter | AB49: kubikmeter | AC49: mètre cube | AD49: metro cubo | AF49: Candidate | AG49: 2026-06-30T12:00:00Z | AH49: KBOB
E50: storey-height | F50: geschosshohe | H50: =IFERROR(INDEX(Rules!$F:$F,MATCH(G51,Rules!$E:$E,0)),"") | I50: =IFERROR(INDEX(Rules!$G:$G,MATCH(G51,Rules!$E:$E,0)),"") | J50: =IFERROR(INDEX(Rules!$H:$H,MATCH(G51,Rules!$E:$E,0)),"") | K50: Storey height | L50: Geschosshöhe | O50: Property for specifying the the storey height. | P50: Merkmal zur Angabe der der Geschosshöhe. | S50: INTEGER | T50: IfcInteger | W50: https://identifier.buildingsmart.org/uri/buildingsmart/ifc/4.3/prop/NetHeight | X50: https://identifier.buildingsmart.org/uri/buildingsmart/ifc/4.3/class/Qto_BuildingStoreyBaseQuantities | AF50: Candidate | AG50: 2026-06-30T12:00:00Z | AH50: KBOB
E51: storey-area | F51: geschossflache | H51: =IFERROR(INDEX(Rules!$F:$F,MATCH(G52,Rules!$E:$E,0)),"") | I51: =IFERROR(INDEX(Rules!$G:$G,MATCH(G52,Rules!$E:$E,0)),"") | J51: =IFERROR(INDEX(Rules!$H:$H,MATCH(G52,Rules!$E:$E,0)),"") | K51: Storey area | L51: Geschossfläche | O51: Property for specifying the the storey area. | P51: Merkmal zur Angabe der der Geschossfläche. | S51: REAL | T51: IfcAreaMeasure | W51: https://identifier.buildingsmart.org/uri/buildingsmart/ifc/4.3/prop/GrossFloorArea | X51: https://identifier.buildingsmart.org/uri/buildingsmart/ifc/4.3/class/Qto_BuildingStoreyBaseQuantities | Y51: m² | Z51: http://qudt.org/vocab/unit/M2 | AA51: square meter | AB51: quadratmeter | AC51: mètre carré | AD51: metro quadrato | AF51: Candidate | AG51: 2026-06-30T12:00:00Z | AH51: KBOB
E52: external-storey-area | F52: aussengeschossflache | H52: =IFERROR(INDEX(Rules!$F:$F,MATCH(G53,Rules!$E:$E,0)),"") | I52: =IFERROR(INDEX(Rules!$G:$G,MATCH(G53,Rules!$E:$E,0)),"") | J52: =IFERROR(INDEX(Rules!$H:$H,MATCH(G53,Rules!$E:$E,0)),"") | K52: External storey area | L52: Aussengeschossfläche | O52: Property for specifying the the external storey area. | P52: Merkmal zur Angabe der der Aussengeschossfläche. | S52: REAL | T52: IfcAreaMeasure | W52: https://identifier.buildingsmart.org/uri/buildingsmart/ifc/4.3/prop/GrossFloorArea | X52: https://identifier.buildingsmart.org/uri/buildingsmart/ifc/4.3/class/Qto_BuildingStoreyBaseQuantities | Y52: m² | Z52: http://qudt.org/vocab/unit/M2 | AA52: square meter | AB52: quadratmeter | AC52: mètre carré | AD52: metro quadrato | AF52: Candidate | AG52: 2026-06-30T12:00:00Z | AH52: KBOB
E53: description | F53: beschreibung | H53: =IFERROR(INDEX(Rules!$F:$F,MATCH(G54,Rules!$E:$E,0)),"") | I53: =IFERROR(INDEX(Rules!$G:$G,MATCH(G54,Rules!$E:$E,0)),"") | J53: =IFERROR(INDEX(Rules!$H:$H,MATCH(G54,Rules!$E:$E,0)),"") | K53: Description | L53: Beschreibung | O53: Property for specifying the description. | P53: Merkmal zur Angabe von der Beschreibung. | S53: STRING | T53: IfcLabel | W53: https://identifier.buildingsmart.org/uri/buildingsmart/ifc/4.3/prop/Description | AF53: Candidate | AG53: 2026-06-30T12:00:00Z | AH53: KBOB
E54: above-ground | F54: oberirdisch | H54: =IFERROR(INDEX(Rules!$F:$F,MATCH(G55,Rules!$E:$E,0)),"") | I54: =IFERROR(INDEX(Rules!$G:$G,MATCH(G55,Rules!$E:$E,0)),"") | J54: =IFERROR(INDEX(Rules!$H:$H,MATCH(G55,Rules!$E:$E,0)),"") | K54: Above ground | L54: Oberirdisch | O54: Property for specifying whether the storey is above ground. | P54: Merkmal zur Angabe, ob das Geschoss oberirdisch liegt. | S54: STRING | T54: IfcLabel | W54: https://identifier.buildingsmart.org/uri/buildingsmart/ifc/4.3/prop/AboveGround | X54: https://identifier.buildingsmart.org/uri/buildingsmart/ifc/4.3/class/Pset_BuildingStoreyCommon | AF54: Candidate | AG54: 2026-06-30T12:00:00Z | AH54: KBOB
E55: room-id | F55: raum-id | H55: =IFERROR(INDEX(Rules!$F:$F,MATCH(G56,Rules!$E:$E,0)),"") | I55: =IFERROR(INDEX(Rules!$G:$G,MATCH(G56,Rules!$E:$E,0)),"") | J55: =IFERROR(INDEX(Rules!$H:$H,MATCH(G56,Rules!$E:$E,0)),"") | K55: Room ID | L55: Raum ID | O55: Property for uniquely identifying rooms. | P55: Merkmal zur eindeutigen Identifikation von Räumen. | S55: STRING | T55: IfcLabel | AF55: Candidate | AG55: 2026-06-30T12:00:00Z | AH55: KBOB
E56: operational-room-number | F56: raumnummer-betrieb | H56: =IFERROR(INDEX(Rules!$F:$F,MATCH(G57,Rules!$E:$E,0)),"") | I56: =IFERROR(INDEX(Rules!$G:$G,MATCH(G57,Rules!$E:$E,0)),"") | J56: =IFERROR(INDEX(Rules!$H:$H,MATCH(G57,Rules!$E:$E,0)),"") | K56: Operational room number | L56: Raumnummer Betrieb | O56: Property for specifying the operational room number. | P56: Merkmal zur Angabe von der betrieblichen Raumnummer. | S56: STRING | T56: IfcLabel | AF56: Candidate | AG56: 2026-06-30T12:00:00Z | AH56: KBOB
E57: room-designation | F57: raumbezeichnung | H57: =IFERROR(INDEX(Rules!$F:$F,MATCH(G58,Rules!$E:$E,0)),"") | I57: =IFERROR(INDEX(Rules!$G:$G,MATCH(G58,Rules!$E:$E,0)),"") | J57: =IFERROR(INDEX(Rules!$H:$H,MATCH(G58,Rules!$E:$E,0)),"") | K57: Room designation | L57: Raumbezeichnung | O57: Property for specifying the room designation. | P57: Merkmal zur Angabe von der Raumbezeichnung. | S57: STRING | T57: IfcLabel | W57: https://identifier.buildingsmart.org/uri/buildingsmart/ifc/4.3/prop/LongName | AF57: Candidate | AG57: 2026-06-30T12:00:00Z | AH57: KBOB
E58: room-labelled | F58: raum-beschriftet | H58: =IFERROR(INDEX(Rules!$F:$F,MATCH(G59,Rules!$E:$E,0)),"") | I58: =IFERROR(INDEX(Rules!$G:$G,MATCH(G59,Rules!$E:$E,0)),"") | J58: =IFERROR(INDEX(Rules!$H:$H,MATCH(G59,Rules!$E:$E,0)),"") | K58: Room labelled | L58: Raum beschriftet | O58: Property for specifying whether the room is labelled. | P58: Merkmal zur Angabe, ob der Raum beschriftet ist. | S58: STRING | T58: IfcLabel | W58: https://identifier.buildingsmart.org/uri/buildingsmart/ifc/4.3/prop/Name | AF58: Candidate | AG58: 2026-06-30T12:00:00Z | AH58: KBOB
E59: room-type | F59: raumtyp | H59: =IFERROR(INDEX(Rules!$F:$F,MATCH(G60,Rules!$E:$E,0)),"") | I59: =IFERROR(INDEX(Rules!$G:$G,MATCH(G60,Rules!$E:$E,0)),"") | J59: =IFERROR(INDEX(Rules!$H:$H,MATCH(G60,Rules!$E:$E,0)),"") | K59: Room type | L59: Raumtyp | O59: Property for specifying the room type. | P59: Merkmal zur Angabe von dem Raumtyp. | S59: STRING | T59: IfcLabel | W59: https://identifier.buildingsmart.org/uri/buildingsmart/ifc/4.3/prop/OccupancyType | X59: https://identifier.buildingsmart.org/uri/buildingsmart/ifc/4.3/class/Pset_SpaceOccupancyRequirements | AF59: Candidate | AG59: 2026-06-30T12:00:00Z | AH59: KBOB
E60: cleaning-group | F60: reinigungsgruppe | H60: =IFERROR(INDEX(Rules!$F:$F,MATCH(G61,Rules!$E:$E,0)),"") | I60: =IFERROR(INDEX(Rules!$G:$G,MATCH(G61,Rules!$E:$E,0)),"") | J60: =IFERROR(INDEX(Rules!$H:$H,MATCH(G61,Rules!$E:$E,0)),"") | K60: Cleaning group | L60: Reinigungsgruppe | O60: Property for specifying the cleaning group. | P60: Merkmal zur Angabe von der Reinigungsgruppe. | S60: STRING | T60: IfcLabel | AF60: Candidate | AG60: 2026-06-30T12:00:00Z | AH60: KBOB
E61: area-type-sia-416 | F61: flachenart-sia-416 | H61: =IFERROR(INDEX(Rules!$F:$F,MATCH(G62,Rules!$E:$E,0)),"") | I61: =IFERROR(INDEX(Rules!$G:$G,MATCH(G62,Rules!$E:$E,0)),"") | J61: =IFERROR(INDEX(Rules!$H:$H,MATCH(G62,Rules!$E:$E,0)),"") | K61: Area type SIA 416 | L61: Flächenart SIA 416 | O61: Property for specifying the area type according to SIA 416. | P61: Merkmal zur Angabe von der Flächenart nach SIA 416. | S61: STRING | T61: IfcLabel | W61: https://identifier.buildingsmart.org/uri/buildingsmart/ifc/4.3/prop/Category | AF61: Candidate | AG61: 2026-06-30T12:00:00Z | AH61: KBOB
E62: area-type-d0165 | F62: flachenart-d0165 | H62: =IFERROR(INDEX(Rules!$F:$F,MATCH(G63,Rules!$E:$E,0)),"") | I62: =IFERROR(INDEX(Rules!$G:$G,MATCH(G63,Rules!$E:$E,0)),"") | J62: =IFERROR(INDEX(Rules!$H:$H,MATCH(G63,Rules!$E:$E,0)),"") | K62: Area type d0165 | L62: Flächenart d0165 | O62: Property for specifying the area type according to d0165. | P62: Merkmal zur Angabe von der Flächenart nach d0165. | S62: STRING | T62: IfcLabel | W62: https://identifier.buildingsmart.org/uri/buildingsmart/ifc/4.3/prop/Category | AF62: Candidate | AG62: 2026-06-30T12:00:00Z | AH62: KBOB
E63: net-room-volume | F63: raumvolumen-netto | H63: =IFERROR(INDEX(Rules!$F:$F,MATCH(G64,Rules!$E:$E,0)),"") | I63: =IFERROR(INDEX(Rules!$G:$G,MATCH(G64,Rules!$E:$E,0)),"") | J63: =IFERROR(INDEX(Rules!$H:$H,MATCH(G64,Rules!$E:$E,0)),"") | K63: Net room volume | L63: Raumvolumen Netto | O63: Property for specifying the the net room volume. | P63: Merkmal zur Angabe der dem Netto-Raumvolumen. | S63: REAL | T63: IfcVolumeMeasure | W63: https://identifier.buildingsmart.org/uri/buildingsmart/ifc/4.3/prop/NetVolume | X63: https://identifier.buildingsmart.org/uri/buildingsmart/ifc/4.3/class/Qto_BodyGeometryValidation | Y63: m³ | Z63: http://qudt.org/vocab/unit/M3 | AA63: cubic meter | AB63: kubikmeter | AC63: mètre cube | AD63: metro cubo | AF63: Candidate | AG63: 2026-06-30T12:00:00Z | AH63: KBOB
E64: usable-height | F64: nutzhohe | H64: =IFERROR(INDEX(Rules!$F:$F,MATCH(G65,Rules!$E:$E,0)),"") | I64: =IFERROR(INDEX(Rules!$G:$G,MATCH(G65,Rules!$E:$E,0)),"") | J64: =IFERROR(INDEX(Rules!$H:$H,MATCH(G65,Rules!$E:$E,0)),"") | K64: Usable height | L64: Nutzhöhe | O64: Property for specifying the the usable height. | P64: Merkmal zur Angabe der der Nutzhöhe. | S64: INTEGER | T64: IfcInteger | W64: https://identifier.buildingsmart.org/uri/buildingsmart/ifc/4.3/prop/NetHeight | X64: https://identifier.buildingsmart.org/uri/buildingsmart/ifc/4.3/class/Qto_BuildingStoreyBaseQuantities | AF64: Candidate | AG64: 2026-06-30T12:00:00Z | AH64: KBOB
E65: clear-room-height | F65: lichte-raumhohe | H65: =IFERROR(INDEX(Rules!$F:$F,MATCH(G66,Rules!$E:$E,0)),"") | I65: =IFERROR(INDEX(Rules!$G:$G,MATCH(G66,Rules!$E:$E,0)),"") | J65: =IFERROR(INDEX(Rules!$H:$H,MATCH(G66,Rules!$E:$E,0)),"") | K65: Clear room height | L65: Lichte Raumhöhe | O65: Property for specifying the the clear room height. | P65: Merkmal zur Angabe der der lichten Raumhöhe. | S65: INTEGER | T65: IfcInteger | W65: https://identifier.buildingsmart.org/uri/buildingsmart/ifc/4.3/prop/ClearHeight | X65: https://identifier.buildingsmart.org/uri/buildingsmart/ifc/4.3/class/Pset_TransportElementElevator | AF65: Candidate | AG65: 2026-06-30T12:00:00Z | AH65: KBOB
E66: gross-room-area | F66: raumflache-brutto | H66: =IFERROR(INDEX(Rules!$F:$F,MATCH(G67,Rules!$E:$E,0)),"") | I66: =IFERROR(INDEX(Rules!$G:$G,MATCH(G67,Rules!$E:$E,0)),"") | J66: =IFERROR(INDEX(Rules!$H:$H,MATCH(G67,Rules!$E:$E,0)),"") | K66: Gross room area | L66: Raumfläche Brutto | O66: Property for specifying the the gross room area. | P66: Merkmal zur Angabe der der Brutto-Raumfläche. | S66: REAL | T66: IfcAreaMeasure | W66: https://identifier.buildingsmart.org/uri/buildingsmart/ifc/4.3/prop/GrossFloorArea | X66: https://identifier.buildingsmart.org/uri/buildingsmart/ifc/4.3/class/Qto_SpaceBaseQuantities | Y66: m² | Z66: http://qudt.org/vocab/unit/M2 | AA66: square meter | AB66: quadratmeter | AC66: mètre carré | AD66: metro quadrato | AF66: Candidate | AG66: 2026-06-30T12:00:00Z | AH66: KBOB
E67: net-room-area | F67: raumflache-netto | H67: =IFERROR(INDEX(Rules!$F:$F,MATCH(G68,Rules!$E:$E,0)),"") | I67: =IFERROR(INDEX(Rules!$G:$G,MATCH(G68,Rules!$E:$E,0)),"") | J67: =IFERROR(INDEX(Rules!$H:$H,MATCH(G68,Rules!$E:$E,0)),"") | K67: Net room area | L67: Raumfläche Netto | O67: Property for specifying the the net room area. | P67: Merkmal zur Angabe der der Netto-Raumfläche. | S67: REAL | T67: IfcAreaMeasure | W67: https://identifier.buildingsmart.org/uri/buildingsmart/ifc/4.3/prop/NetFloorArea | X67: https://identifier.buildingsmart.org/uri/buildingsmart/ifc/4.3/class/Qto_SpaceBaseQuantities | Y67: m² | Z67: http://qudt.org/vocab/unit/M2 | AA67: square meter | AB67: quadratmeter | AC67: mètre carré | AD67: metro quadrato | AF67: Candidate | AG67: 2026-06-30T12:00:00Z | AH67: KBOB
E68: area-load | F68: flachenlast | H68: =IFERROR(INDEX(Rules!$F:$F,MATCH(G69,Rules!$E:$E,0)),"") | I68: =IFERROR(INDEX(Rules!$G:$G,MATCH(G69,Rules!$E:$E,0)),"") | J68: =IFERROR(INDEX(Rules!$H:$H,MATCH(G69,Rules!$E:$E,0)),"") | K68: Area load | L68: Flächenlast | O68: Property for specifying the the area load. | P68: Merkmal zur Angabe der der Flächenlast. | S68: INTEGER | T68: IfcInteger | W68: https://identifier.buildingsmart.org/uri/buildingsmart/ifc/4.3/prop/LoadBearingCapacity | X68: https://identifier.buildingsmart.org/uri/buildingsmart/ifc/4.3/class/Pset_BuildingStoreyCommon | Y68: kN/m² | AF68: Candidate | AG68: 2026-06-30T12:00:00Z | AH68: KBOB
E69: point-load | F69: punktlast | H69: =IFERROR(INDEX(Rules!$F:$F,MATCH(G70,Rules!$E:$E,0)),"") | I69: =IFERROR(INDEX(Rules!$G:$G,MATCH(G70,Rules!$E:$E,0)),"") | J69: =IFERROR(INDEX(Rules!$H:$H,MATCH(G70,Rules!$E:$E,0)),"") | K69: Point load | L69: Punktlast | O69: Property for specifying the the point load. | P69: Merkmal zur Angabe der der Punktlast. | S69: INTEGER | T69: IfcInteger | W69: https://identifier.buildingsmart.org/uri/buildingsmart/ifc/4.3/prop/LoadBearingCapacity | X69: https://identifier.buildingsmart.org/uri/buildingsmart/ifc/4.3/class/Pset_BuildingStoreyCommon | Y69: kN | Z69: http://qudt.org/vocab/unit/KiloN | AA69: kilonewton | AB69: kilonewton | AC69: kilonewton | AD69: chilonewton | AF69: Candidate | AG69: 2026-06-30T12:00:00Z | AH69: KBOB
E70: planned-occupancy | F70: personenbelegung-geplant | H70: =IFERROR(INDEX(Rules!$F:$F,MATCH(G71,Rules!$E:$E,0)),"") | I70: =IFERROR(INDEX(Rules!$G:$G,MATCH(G71,Rules!$E:$E,0)),"") | J70: =IFERROR(INDEX(Rules!$H:$H,MATCH(G71,Rules!$E:$E,0)),"") | K70: Planned occupancy | L70: Personenbelegung Geplant | O70: Property for specifying the the planned occupancy. | P70: Merkmal zur Angabe der der geplanten Personenbelegung. | S70: INTEGER | T70: IfcInteger | W70: https://identifier.buildingsmart.org/uri/buildingsmart/ifc/4.3/prop/OccupancyNumber | X70: https://identifier.buildingsmart.org/uri/buildingsmart/ifc/4.3/class/Pset_SpaceOccupancyRequirements | AF70: Candidate | AG70: 2026-06-30T12:00:00Z | AH70: KBOB
E71: actual-occupancy | F71: personenbelegung-ist | H71: =IFERROR(INDEX(Rules!$F:$F,MATCH(G72,Rules!$E:$E,0)),"") | I71: =IFERROR(INDEX(Rules!$G:$G,MATCH(G72,Rules!$E:$E,0)),"") | J71: =IFERROR(INDEX(Rules!$H:$H,MATCH(G72,Rules!$E:$E,0)),"") | K71: Actual occupancy | L71: Personenbelegung Ist | O71: Property for specifying the the actual occupancy. | P71: Merkmal zur Angabe der der tatsächlichen Personenbelegung. | S71: INTEGER | T71: IfcInteger | W71: https://identifier.buildingsmart.org/uri/buildingsmart/ifc/4.3/prop/OccupancyNumber | X71: https://identifier.buildingsmart.org/uri/buildingsmart/ifc/4.3/class/Pset_SpaceOccupancyRequirements | AF71: Candidate | AG71: 2026-06-30T12:00:00Z | AH71: KBOB
E72: energy-reference-area | F72: energiebezugsflache | H72: =IFERROR(INDEX(Rules!$F:$F,MATCH(G73,Rules!$E:$E,0)),"") | I72: =IFERROR(INDEX(Rules!$G:$G,MATCH(G73,Rules!$E:$E,0)),"") | J72: =IFERROR(INDEX(Rules!$H:$H,MATCH(G73,Rules!$E:$E,0)),"") | K72: Energy reference area | L72: Energiebezugsfläche | O72: Property for specifying the the energy reference area. | P72: Merkmal zur Angabe der der Energiebezugsfläche. | S72: STRING | T72: IfcLabel | W72: https://identifier.buildingsmart.org/uri/buildingsmart/ifc/4.3/prop/NetPlannedArea | X72: https://identifier.buildingsmart.org/uri/buildingsmart/ifc/4.3/class/Pset_SpaceCommon | AF72: Candidate | AG72: 2026-06-30T12:00:00Z | AH72: KBOB
E73: temperature | F73: temperatur | H73: =IFERROR(INDEX(Rules!$F:$F,MATCH(G74,Rules!$E:$E,0)),"") | I73: =IFERROR(INDEX(Rules!$G:$G,MATCH(G74,Rules!$E:$E,0)),"") | J73: =IFERROR(INDEX(Rules!$H:$H,MATCH(G74,Rules!$E:$E,0)),"") | K73: Temperature | L73: Temperatur | O73: Property for specifying the the temperature. | P73: Merkmal zur Angabe der der Temperatur. | S73: STRING | T73: IfcLabel | W73: https://identifier.buildingsmart.org/uri/buildingsmart/ifc/4.3/prop/ReferenceEnvironmentTemperature | X73: https://identifier.buildingsmart.org/uri/buildingsmart/ifc/4.3/class/Pset_EnvironmentalCondition | AF73: Candidate | AG73: 2026-06-30T12:00:00Z | AH73: KBOB
E74: escape-route | F74: fluchtweg | H74: =IFERROR(INDEX(Rules!$F:$F,MATCH(G75,Rules!$E:$E,0)),"") | I74: =IFERROR(INDEX(Rules!$G:$G,MATCH(G75,Rules!$E:$E,0)),"") | J74: =IFERROR(INDEX(Rules!$H:$H,MATCH(G75,Rules!$E:$E,0)),"") | K74: Escape route | L74: Fluchtweg | O74: Property for specifying the escape route. | P74: Merkmal zur Angabe von dem Fluchtweg. | S74: STRING | T74: IfcLabel | AF74: Candidate | AG74: 2026-06-30T12:00:00Z | AH74: KBOB
E75: window-area | F75: fensterflache | H75: =IFERROR(INDEX(Rules!$F:$F,MATCH(G76,Rules!$E:$E,0)),"") | I75: =IFERROR(INDEX(Rules!$G:$G,MATCH(G76,Rules!$E:$E,0)),"") | J75: =IFERROR(INDEX(Rules!$H:$H,MATCH(G76,Rules!$E:$E,0)),"") | K75: Window area | L75: Fensterfläche | O75: Property for specifying the the window area. | P75: Merkmal zur Angabe der der Fensterfläche. | S75: REAL | T75: IfcAreaMeasure | Y75: m² | Z75: http://qudt.org/vocab/unit/M2 | AA75: square meter | AB75: quadratmeter | AC75: mètre carré | AD75: metro quadrato | AF75: Candidate | AG75: 2026-06-30T12:00:00Z | AH75: KBOB
E76: openable-window | F76: fenster-offenbar | H76: =IFERROR(INDEX(Rules!$F:$F,MATCH(G77,Rules!$E:$E,0)),"") | I76: =IFERROR(INDEX(Rules!$G:$G,MATCH(G77,Rules!$E:$E,0)),"") | J76: =IFERROR(INDEX(Rules!$H:$H,MATCH(G77,Rules!$E:$E,0)),"") | K76: Openable window | L76: Fenster Öffenbar | O76: Property for specifying whether the window can be opened. | P76: Merkmal zur Angabe, ob das Fenster geöffnet werden kann. | S76: STRING | T76: IfcLabel | W76: https://identifier.buildingsmart.org/uri/buildingsmart/ifc/4.3/prop/OperationType | AF76: Candidate | AG76: 2026-06-30T12:00:00Z | AH76: KBOB
E77: room-user | F77: raumnutzer | H77: =IFERROR(INDEX(Rules!$F:$F,MATCH(G78,Rules!$E:$E,0)),"") | I77: =IFERROR(INDEX(Rules!$G:$G,MATCH(G78,Rules!$E:$E,0)),"") | J77: =IFERROR(INDEX(Rules!$H:$H,MATCH(G78,Rules!$E:$E,0)),"") | K77: Room user | L77: Raumnutzer | O77: Property for specifying the room user. | P77: Merkmal zur Angabe von dem Raumnutzer. | S77: STRING | T77: IfcLabel | W77: https://identifier.buildingsmart.org/uri/buildingsmart/ifc/4.3/prop/OccupancyType | X77: https://identifier.buildingsmart.org/uri/buildingsmart/ifc/4.3/class/Pset_SpaceOccupancyRequirements | AF77: Candidate | AG77: 2026-06-30T12:00:00Z | AH77: KBOB
E78: floor-covering | F78: bodenbelag | H78: =IFERROR(INDEX(Rules!$F:$F,MATCH(G79,Rules!$E:$E,0)),"") | I78: =IFERROR(INDEX(Rules!$G:$G,MATCH(G79,Rules!$E:$E,0)),"") | J78: =IFERROR(INDEX(Rules!$H:$H,MATCH(G79,Rules!$E:$E,0)),"") | K78: Floor covering | L78: Bodenbelag | O78: Property for specifying the floor covering. | P78: Merkmal zur Angabe von dem Bodenbelag. | S78: STRING | T78: IfcLabel | W78: https://identifier.buildingsmart.org/uri/buildingsmart/ifc/4.3/prop/FloorCovering | X78: https://identifier.buildingsmart.org/uri/buildingsmart/ifc/4.3/class/Pset_SpaceCoveringRequirements | AF78: Candidate | AG78: 2026-06-30T12:00:00Z | AH78: KBOB
E79: ceiling-material | F79: deckenmaterial | H79: =IFERROR(INDEX(Rules!$F:$F,MATCH(G80,Rules!$E:$E,0)),"") | I79: =IFERROR(INDEX(Rules!$G:$G,MATCH(G80,Rules!$E:$E,0)),"") | J79: =IFERROR(INDEX(Rules!$H:$H,MATCH(G80,Rules!$E:$E,0)),"") | K79: Ceiling material | L79: Deckenmaterial | O79: Property for specifying the ceiling material. | P79: Merkmal zur Angabe von dem Deckenmaterial. | S79: STRING | T79: IfcLabel | W79: https://identifier.buildingsmart.org/uri/buildingsmart/ifc/4.3/prop/CeilingCovering | X79: https://identifier.buildingsmart.org/uri/buildingsmart/ifc/4.3/class/Pset_SpaceCoveringRequirements | AF79: Candidate | AG79: 2026-06-30T12:00:00Z | AH79: KBOB
E80: wall-covering | F80: wandbelag | H80: =IFERROR(INDEX(Rules!$F:$F,MATCH(G81,Rules!$E:$E,0)),"") | I80: =IFERROR(INDEX(Rules!$G:$G,MATCH(G81,Rules!$E:$E,0)),"") | J80: =IFERROR(INDEX(Rules!$H:$H,MATCH(G81,Rules!$E:$E,0)),"") | K80: Wall covering | L80: Wandbelag | O80: Property for specifying the wall covering. | P80: Merkmal zur Angabe von dem Wandbelag. | S80: STRING | T80: IfcLabel | W80: https://identifier.buildingsmart.org/uri/buildingsmart/ifc/4.3/prop/WallCovering | X80: https://identifier.buildingsmart.org/uri/buildingsmart/ifc/4.3/class/Pset_SpaceCoveringRequirements | AF80: Candidate | AG80: 2026-06-30T12:00:00Z | AH80: KBOB
E81: air-change-rate | F81: luftwechselrate | H81: =IFERROR(INDEX(Rules!$F:$F,MATCH(G82,Rules!$E:$E,0)),"") | I81: =IFERROR(INDEX(Rules!$G:$G,MATCH(G82,Rules!$E:$E,0)),"") | J81: =IFERROR(INDEX(Rules!$H:$H,MATCH(G82,Rules!$E:$E,0)),"") | K81: Air change rate | L81: Luftwechselrate | O81: Property for specifying the the air change rate. | P81: Merkmal zur Angabe der der Luftwechselrate. | S81: STRING | T81: IfcLabel | W81: https://identifier.buildingsmart.org/uri/buildingsmart/ifc/4.3/prop/MechanicalVentilationRate | X81: https://identifier.buildingsmart.org/uri/buildingsmart/ifc/4.3/class/Pset_SpaceHVACDesign | AF81: Candidate | AG81: 2026-06-30T12:00:00Z | AH81: KBOB
E82: solar-shading | F82: sonnenschutz | H82: =IFERROR(INDEX(Rules!$F:$F,MATCH(G83,Rules!$E:$E,0)),"") | I82: =IFERROR(INDEX(Rules!$G:$G,MATCH(G83,Rules!$E:$E,0)),"") | J82: =IFERROR(INDEX(Rules!$H:$H,MATCH(G83,Rules!$E:$E,0)),"") | K82: Solar shading | L82: Sonnenschutz | O82: Property for specifying the solar shading. | P82: Merkmal zur Angabe von dem Sonnenschutz. | S82: STRING | T82: IfcLabel | AF82: Candidate | AG82: 2026-06-30T12:00:00Z | AH82: KBOB
E83: ventilation | F83: beluftung | H83: =IFERROR(INDEX(Rules!$F:$F,MATCH(G84,Rules!$E:$E,0)),"") | I83: =IFERROR(INDEX(Rules!$G:$G,MATCH(G84,Rules!$E:$E,0)),"") | J83: =IFERROR(INDEX(Rules!$H:$H,MATCH(G84,Rules!$E:$E,0)),"") | K83: Ventilation | L83: Belüftung | O83: Property for specifying the ventilation. | P83: Merkmal zur Angabe von der Belüftung. | S83: INTEGER | T83: IfcInteger | W83: https://identifier.buildingsmart.org/uri/buildingsmart/ifc/4.3/prop/MechanicalVentilationRate | X83: https://identifier.buildingsmart.org/uri/buildingsmart/ifc/4.3/class/Pset_SpaceHVACDesign | Y83: m³/h | AF83: Candidate | AG83: 2026-06-30T12:00:00Z | AH83: KBOB
E84: air-conditioned | F84: klimatisiert | H84: =IFERROR(INDEX(Rules!$F:$F,MATCH(G85,Rules!$E:$E,0)),"") | I84: =IFERROR(INDEX(Rules!$G:$G,MATCH(G85,Rules!$E:$E,0)),"") | J84: =IFERROR(INDEX(Rules!$H:$H,MATCH(G85,Rules!$E:$E,0)),"") | K84: Air-conditioned | L84: Klimatisiert | O84: Property for specifying whether the room is air-conditioned. | P84: Merkmal zur Angabe, ob der Raum klimatisiert ist. | S84: INTEGER | T84: IfcInteger | Y84: °C | AF84: Candidate | AG84: 2026-06-30T12:00:00Z | AH84: KBOB
E85: humidity | F85: luftfeuchtigkeit | H85: =IFERROR(INDEX(Rules!$F:$F,MATCH(G86,Rules!$E:$E,0)),"") | I85: =IFERROR(INDEX(Rules!$G:$G,MATCH(G86,Rules!$E:$E,0)),"") | J85: =IFERROR(INDEX(Rules!$H:$H,MATCH(G86,Rules!$E:$E,0)),"") | K85: Humidity | L85: Luftfeuchtigkeit | O85: Property for specifying the the humidity. | P85: Merkmal zur Angabe der der Luftfeuchtigkeit. | S85: INTEGER | T85: IfcInteger | W85: https://identifier.buildingsmart.org/uri/buildingsmart/ifc/4.3/prop/ReferenceAirRelativeHumidity | X85: https://identifier.buildingsmart.org/uri/buildingsmart/ifc/4.3/class/Pset_EnvironmentalCondition | Y85: % | Z85: http://qudt.org/vocab/unit/PERCENT | AA85: percent | AF85: Candidate | AG85: 2026-06-30T12:00:00Z | AH85: KBOB
E86: humidified | F86: befeuchtet | H86: =IFERROR(INDEX(Rules!$F:$F,MATCH(G87,Rules!$E:$E,0)),"") | I86: =IFERROR(INDEX(Rules!$G:$G,MATCH(G87,Rules!$E:$E,0)),"") | J86: =IFERROR(INDEX(Rules!$H:$H,MATCH(G87,Rules!$E:$E,0)),"") | K86: Humidified | L86: Befeuchtet | O86: Property for specifying whether the room is humidified. | P86: Merkmal zur Angabe, ob der Raum befeuchtet wird. | S86: STRING | T86: IfcLabel | W86: https://identifier.buildingsmart.org/uri/buildingsmart/ifc/4.3/prop/ReferenceAirRelativeHumidity | X86: https://identifier.buildingsmart.org/uri/buildingsmart/ifc/4.3/class/Pset_EnvironmentalCondition | AF86: Candidate | AG86: 2026-06-30T12:00:00Z | AH86: KBOB
E87: dehumidified | F87: entfeuchtet | H87: =IFERROR(INDEX(Rules!$F:$F,MATCH(G88,Rules!$E:$E,0)),"") | I87: =IFERROR(INDEX(Rules!$G:$G,MATCH(G88,Rules!$E:$E,0)),"") | J87: =IFERROR(INDEX(Rules!$H:$H,MATCH(G88,Rules!$E:$E,0)),"") | K87: Dehumidified | L87: Entfeuchtet | O87: Property for specifying whether the room is dehumidified. | P87: Merkmal zur Angabe, ob der Raum entfeuchtet wird. | S87: STRING | T87: IfcLabel | W87: https://identifier.buildingsmart.org/uri/buildingsmart/ifc/4.3/prop/ReferenceAirRelativeHumidity | X87: https://identifier.buildingsmart.org/uri/buildingsmart/ifc/4.3/class/Pset_EnvironmentalCondition | AF87: Candidate | AG87: 2026-06-30T12:00:00Z | AH87: KBOB
E88: pneumatic-tube-system | F88: rohrpost | H88: =IFERROR(INDEX(Rules!$F:$F,MATCH(G89,Rules!$E:$E,0)),"") | I88: =IFERROR(INDEX(Rules!$G:$G,MATCH(G89,Rules!$E:$E,0)),"") | J88: =IFERROR(INDEX(Rules!$H:$H,MATCH(G89,Rules!$E:$E,0)),"") | K88: Pneumatic tube system | L88: Rohrpost | O88: Property for specifying whether a pneumatic tube system is present. | P88: Merkmal zur Angabe, ob eine Rohrpostanlage vorhanden ist. | S88: STRING | T88: IfcLabel | AF88: Candidate | AG88: 2026-06-30T12:00:00Z | AH88: KBOB
E89: rentability | F89: vermietbarkeit | H89: =IFERROR(INDEX(Rules!$F:$F,MATCH(G90,Rules!$E:$E,0)),"") | I89: =IFERROR(INDEX(Rules!$G:$G,MATCH(G90,Rules!$E:$E,0)),"") | J89: =IFERROR(INDEX(Rules!$H:$H,MATCH(G90,Rules!$E:$E,0)),"") | K89: Rentability | L89: Vermietbarkeit | O89: Property for specifying whether the room or object is rentable. | P89: Merkmal zur Angabe, ob der Raum oder das Objekt vermietbar ist. | S89: STRING | T89: IfcLabel | W89: https://identifier.buildingsmart.org/uri/buildingsmart/ifc/4.3/prop/MarketCategory | X89: https://identifier.buildingsmart.org/uri/buildingsmart/ifc/4.3/class/Pset_BuildingUse | AF89: Candidate | AG89: 2026-06-30T12:00:00Z | AH89: KBOB
E90: component-id | F90: bauteil-id | H90: =IFERROR(INDEX(Rules!$F:$F,MATCH(G91,Rules!$E:$E,0)),"") | I90: =IFERROR(INDEX(Rules!$G:$G,MATCH(G91,Rules!$E:$E,0)),"") | J90: =IFERROR(INDEX(Rules!$H:$H,MATCH(G91,Rules!$E:$E,0)),"") | K90: Component ID | L90: Bauteil ID | O90: Property for uniquely identifying components. | P90: Merkmal zur eindeutigen Identifikation von Bauteilen. | S90: STRING | T90: IfcLabel | AF90: Candidate | AG90: 2026-06-30T12:00:00Z | AH90: KBOB
E91: aks | F91: aks | H91: =IFERROR(INDEX(Rules!$F:$F,MATCH(G92,Rules!$E:$E,0)),"") | I91: =IFERROR(INDEX(Rules!$G:$G,MATCH(G92,Rules!$E:$E,0)),"") | J91: =IFERROR(INDEX(Rules!$H:$H,MATCH(G92,Rules!$E:$E,0)),"") | K91: AKS | L91: AKS | O91: Property for specifying the AKS code. | P91: Merkmal zur Angabe von dem AKS-Code. | S91: STRING | T91: IfcLabel | W91: https://identifier.buildingsmart.org/uri/buildingsmart/ifc/4.3/prop/AssetIdentifier | X91: https://identifier.buildingsmart.org/uri/buildingsmart/ifc/4.3/class/Pset_ConstructionOccurence | AF91: Candidate | AG91: 2026-06-30T12:00:00Z | AH91: KBOB
E92: drive | F92: antrieb | H92: =IFERROR(INDEX(Rules!$F:$F,MATCH(G93,Rules!$E:$E,0)),"") | I92: =IFERROR(INDEX(Rules!$G:$G,MATCH(G93,Rules!$E:$E,0)),"") | J92: =IFERROR(INDEX(Rules!$H:$H,MATCH(G93,Rules!$E:$E,0)),"") | K92: Drive | L92: Antrieb | O92: Property for specifying the drive. | P92: Merkmal zur Angabe von dem Antrieb. | S92: STRING | T92: IfcLabel | W92: https://identifier.buildingsmart.org/uri/buildingsmart/ifc/4.3/prop/ActuatorInputPower | X92: https://identifier.buildingsmart.org/uri/buildingsmart/ifc/4.3/class/Pset_ActuatorTypeElectricActuator | AF92: Candidate | AG92: 2026-06-30T12:00:00Z | AH92: KBOB
E93: article-number | F93: artikelnummer | H93: =IFERROR(INDEX(Rules!$F:$F,MATCH(G94,Rules!$E:$E,0)),"") | I93: =IFERROR(INDEX(Rules!$G:$G,MATCH(G94,Rules!$E:$E,0)),"") | J93: =IFERROR(INDEX(Rules!$H:$H,MATCH(G94,Rules!$E:$E,0)),"") | K93: Article number | L93: Artikelnummer | O93: Property for specifying the article number. | P93: Merkmal zur Angabe von der Artikelnummer. | S93: STRING | T93: IfcLabel | W93: https://identifier.buildingsmart.org/uri/buildingsmart/ifc/4.3/prop/ArticleNumber | X93: https://identifier.buildingsmart.org/uri/buildingsmart/ifc/4.3/class/Pset_ManufacturerTypeInformation | AF93: Candidate | AG93: 2026-06-30T12:00:00Z | AH93: KBOB
E94: component-category | F94: bauteilart | H94: =IFERROR(INDEX(Rules!$F:$F,MATCH(G95,Rules!$E:$E,0)),"") | I94: =IFERROR(INDEX(Rules!$G:$G,MATCH(G95,Rules!$E:$E,0)),"") | J94: =IFERROR(INDEX(Rules!$H:$H,MATCH(G95,Rules!$E:$E,0)),"") | K94: Component category | L94: Bauteilart | O94: Property for specifying the component category. | P94: Merkmal zur Angabe von der Bauteilart. | S94: STRING | T94: IfcLabel | W94: https://identifier.buildingsmart.org/uri/buildingsmart/ifc/4.3/prop/ObjectType | AF94: Candidate | AG94: 2026-06-30T12:00:00Z | AH94: KBOB
E95: component-type | F95: bauteiltyp | H95: =IFERROR(INDEX(Rules!$F:$F,MATCH(G96,Rules!$E:$E,0)),"") | I95: =IFERROR(INDEX(Rules!$G:$G,MATCH(G96,Rules!$E:$E,0)),"") | J95: =IFERROR(INDEX(Rules!$H:$H,MATCH(G96,Rules!$E:$E,0)),"") | K95: Component type | L95: Bauteiltyp | O95: Property for specifying the component type. | P95: Merkmal zur Angabe von dem Bauteiltyp. | S95: STRING | T95: IfcLabel | W95: https://identifier.buildingsmart.org/uri/buildingsmart/ifc/4.3/prop/ModelReference | X95: https://identifier.buildingsmart.org/uri/buildingsmart/ifc/4.3/class/Pset_ManufacturerTypeInformation | AF95: Candidate | AG95: 2026-06-30T12:00:00Z | AH95: KBOB
E96: component-name | F96: bauteilname | H96: =IFERROR(INDEX(Rules!$F:$F,MATCH(G97,Rules!$E:$E,0)),"") | I96: =IFERROR(INDEX(Rules!$G:$G,MATCH(G97,Rules!$E:$E,0)),"") | J96: =IFERROR(INDEX(Rules!$H:$H,MATCH(G97,Rules!$E:$E,0)),"") | K96: Component name | L96: Bauteilname | O96: Property for specifying the component name. | P96: Merkmal zur Angabe von dem Bauteilnamen. | S96: STRING | T96: IfcLabel | W96: https://identifier.buildingsmart.org/uri/buildingsmart/ifc/4.3/prop/Name | AF96: Candidate | AG96: 2026-06-30T12:00:00Z | AH96: KBOB
E97: manufacturer | F97: hersteller | H97: =IFERROR(INDEX(Rules!$F:$F,MATCH(G98,Rules!$E:$E,0)),"") | I97: =IFERROR(INDEX(Rules!$G:$G,MATCH(G98,Rules!$E:$E,0)),"") | J97: =IFERROR(INDEX(Rules!$H:$H,MATCH(G98,Rules!$E:$E,0)),"") | K97: Manufacturer | L97: Hersteller | O97: Property for specifying the manufacturer. | P97: Merkmal zur Angabe von dem Hersteller. | S97: STRING | T97: IfcLabel | W97: https://identifier.buildingsmart.org/uri/buildingsmart/ifc/4.3/prop/Manufacturer | X97: https://identifier.buildingsmart.org/uri/buildingsmart/ifc/4.3/class/Pset_ManufacturerTypeInformation | AF97: Candidate | AG97: 2026-06-30T12:00:00Z | AH97: KBOB
E98: product-id | F98: produkt-id | H98: =IFERROR(INDEX(Rules!$F:$F,MATCH(G99,Rules!$E:$E,0)),"") | I98: =IFERROR(INDEX(Rules!$G:$G,MATCH(G99,Rules!$E:$E,0)),"") | J98: =IFERROR(INDEX(Rules!$H:$H,MATCH(G99,Rules!$E:$E,0)),"") | K98: Product ID | L98: Produkt ID | O98: Property for uniquely identifying products. | P98: Merkmal zur eindeutigen Identifikation von Produkten. | S98: STRING | T98: IfcLabel | W98: https://identifier.buildingsmart.org/uri/buildingsmart/ifc/4.3/prop/ModelReference | X98: https://identifier.buildingsmart.org/uri/buildingsmart/ifc/4.3/class/Pset_ManufacturerTypeInformation | AF98: Candidate | AG98: 2026-06-30T12:00:00Z | AH98: KBOB
E99: material | F99: material | H99: =IFERROR(INDEX(Rules!$F:$F,MATCH(G100,Rules!$E:$E,0)),"") | I99: =IFERROR(INDEX(Rules!$G:$G,MATCH(G100,Rules!$E:$E,0)),"") | J99: =IFERROR(INDEX(Rules!$H:$H,MATCH(G100,Rules!$E:$E,0)),"") | K99: Material | L99: Material | O99: Property for specifying the material. | P99: Merkmal zur Angabe von dem Material. | S99: STRING | T99: IfcLabel | AF99: Candidate | AG99: 2026-06-30T12:00:00Z | AH99: KBOB
E100: serial-number | F100: seriennummer | H100: =IFERROR(INDEX(Rules!$F:$F,MATCH(G101,Rules!$E:$E,0)),"") | I100: =IFERROR(INDEX(Rules!$G:$G,MATCH(G101,Rules!$E:$E,0)),"") | J100: =IFERROR(INDEX(Rules!$H:$H,MATCH(G101,Rules!$E:$E,0)),"") | K100: Serial number | L100: Seriennummer | O100: Property for specifying the serial number. | P100: Merkmal zur Angabe von der Seriennummer. | S100: STRING | T100: IfcLabel | W100: https://identifier.buildingsmart.org/uri/buildingsmart/ifc/4.3/prop/SerialNumber | X100: https://identifier.buildingsmart.org/uri/buildingsmart/ifc/4.3/class/Pset_ManufacturerOccurrence | AF100: Candidate | AG100: 2026-06-30T12:00:00Z | AH100: KBOB
...

Sheet Values
A1: Filter | B1: Hinweise zur Handhabung | C1: Enumerations | D1: GUID/URI | E1: Enumeration-ID | F1: Enumeration-Code | G1: Designation (EN) | H1: Bezeichnung (DE) | I1: Désignation (FR) | J1: Designazione (IT) | K1: Enumeration (EN) | L1: Werteliste (DE) | M1: Liste de valeurs (FR) | N1: Lista valori (IT) | O1: Units/Einheit/Unité/Unità | P1: Governance | Q1: Status | R1: Version date | S1: Provenance (PROV)
B2: Erforderlich für Excel
B3: Sprachen
B4: Referenziert / System generiert | D4: multilingual | E4: multilingual | F4: multilingual | G4: EN | H4: DE | I4: FR | J4: IT | K4: EN | L4: DE | M4: FR | N4: IT | O4: multilingual | Q4: multilingual | R4: multilingual | S4: multilingual
B5: Dropdown Liste | D5: system-generated | E5: system-generated | Q5: referenced | R5: referenced | S5: referenced
B6: Validierung | Q6: Rules.Status

Sheet Documents
A1: Filter | B1: Hinweise zur Handhabung | C1: Documents | D1: GUID/URI | E1: Document-ID | F1: Document-Code | G1: DocumentName (EN) | H1: Bezeichnung (DE) | I1: Désignation (FR) | J1: Designazione (IT) | K1: Security level/Sicherheitsstufe/Niveau de sécurité/Livello di sicurezza | L1: Accessibility/Zugänglichkeit/Accessibilité/Accessibilità | M1: Revision | N1: DocumentOwner | O1: Governance | P1: Status | Q1: Version date | R1: Provenance (PROV)
B2: Erforderlich für Excel
B3: Sprachen
B4: Referenziert / System generiert | D4: multilingual | E4: multilingual | F4: multilingual | G4: EN | H4: DE | I4: FR | J4: IT | K4: multilingual | L4: multilingual | M4: multilingual | N4: multilingual | P4: multilingual | Q4: multilingual | R4: multilingual
B5: Dropdown Liste | E5: system-generated | G5: referenced | M5: referenced | N5: referenced | P5: referenced | Q5: referenced | R5: referenced
B6: Validierung | K6: Rules.ISG - Informationssicherheitsgesetz | L6: Rules.FAIR Prinzipien | P6: Rules.Status
E7: kbob-dk-fm-i14y-csv | G7: KBOB DK FM_i14y.csv | H7: KBOB DK FM_i14y.csv | K7: nicht klassifiziert | L7: Zugänglich unentgeltlich | M7: 2026 | N7: KBOB | P7: Candidate | Q7: 2026-06-30T12:00:00Z | R7: KBOB

Sheet GroupOfProperties
A1: Filter | B1: Hinweise zur Handhabung | C1: Group of Properties | D1: GoP-ID | E1: GoP-Code | F1: Designation (EN) | G1: Description (EN) | H1: Beschreibung (DE) | I1: Description (FR) | J1: Descrizione (IT) | K1: Governance | L1: Status | M1: Version date | N1: Provenance (PROV)
B2: Erforderlich für Excel
B3: Sprachen
B4: Referenziert / System generiert | D4: multilingual | E4: multilingual | F4: EN | G4: EN | H4: DE | I4: FR | J4: IT | L4: multilingual | M4: multilingual | N4: multilingual
B5: Dropdown Liste | D5: system-generated | L5: referenced | M5: referenced | N5: referenced
B6: Validierung | L6: Rules.Status
D7: kbob-grundstuck-architekt | E7: KBOB_Grundstuck_Architekt | F7: KBOB_Grundstuck_Architekt | G7: Imported group of properties from old ClassProperty.PropertySetName KBOB_Grundstuck_Architekt. (AI) | H7: Importierte Merkmalsgruppe aus altem ClassProperty.PropertySetName KBOB_Grundstuck_Architekt. (AI) | L7: Candidate | M7: 2026-06-30T12:00:00Z | N7: KBOB
D8: kbob-gebaude-architekt | E8: KBOB_Gebaude_Architekt | F8: KBOB_Gebaude_Architekt | G8: Imported group of properties from old ClassProperty.PropertySetName KBOB_Gebaude_Architekt. (AI) | H8: Importierte Merkmalsgruppe aus altem ClassProperty.PropertySetName KBOB_Gebaude_Architekt. (AI) | L8: Candidate | M8: 2026-06-30T12:00:00Z | N8: KBOB
D9: kbob-gebaude-betriebfm | E9: KBOB_Gebaude_BetriebFM | F9: KBOB_Gebaude_BetriebFM | G9: Imported group of properties from old ClassProperty.PropertySetName KBOB_Gebaude_BetriebFM. (AI) | H9: Importierte Merkmalsgruppe aus altem ClassProperty.PropertySetName KBOB_Gebaude_BetriebFM. (AI) | L9: Candidate | M9: 2026-06-30T12:00:00Z | N9: KBOB
D10: kbob-geschoss-architekt | E10: KBOB_Geschoss_Architekt | F10: KBOB_Geschoss_Architekt | G10: Imported group of properties from old ClassProperty.PropertySetName KBOB_Geschoss_Architekt. (AI) | H10: Importierte Merkmalsgruppe aus altem ClassProperty.PropertySetName KBOB_Geschoss_Architekt. (AI) | L10: Candidate | M10: 2026-06-30T12:00:00Z | N10: KBOB
D11: kbob-geschoss-betriebfm | E11: KBOB_Geschoss_BetriebFM | F11: KBOB_Geschoss_BetriebFM | G11: Imported group of properties from old ClassProperty.PropertySetName KBOB_Geschoss_BetriebFM. (AI) | H11: Importierte Merkmalsgruppe aus altem ClassProperty.PropertySetName KBOB_Geschoss_BetriebFM. (AI) | L11: Candidate | M11: 2026-06-30T12:00:00Z | N11: KBOB
D12: kbob-raum-architekt | E12: KBOB_Raum_Architekt | F12: KBOB_Raum_Architekt | G12: Imported group of properties from old ClassProperty.PropertySetName KBOB_Raum_Architekt. (AI) | H12: Importierte Merkmalsgruppe aus altem ClassProperty.PropertySetName KBOB_Raum_Architekt. (AI) | L12: Candidate | M12: 2026-06-30T12:00:00Z | N12: KBOB
D13: kbob-raum-betriebfm | E13: KBOB_Raum_BetriebFM | F13: KBOB_Raum_BetriebFM | G13: Imported group of properties from old ClassProperty.PropertySetName KBOB_Raum_BetriebFM. (AI) | H13: Importierte Merkmalsgruppe aus altem ClassProperty.PropertySetName KBOB_Raum_BetriebFM. (AI) | L13: Candidate | M13: 2026-06-30T12:00:00Z | N13: KBOB
D14: kbob-raum-hlkksse | E14: KBOB_Raum_HLKKSSE | F14: KBOB_Raum_HLKKSSE | G14: Imported group of properties from old ClassProperty.PropertySetName KBOB_Raum_HLKKSSE. (AI) | H14: Importierte Merkmalsgruppe aus altem ClassProperty.PropertySetName KBOB_Raum_HLKKSSE. (AI) | L14: Candidate | M14: 2026-06-30T12:00:00Z | N14: KBOB
D15: kbob-bauteil-hlkkssearchitekt | E15: KBOB_Bauteil_HLKKSSEArchitekt | F15: KBOB_Bauteil_HLKKSSEArchitekt | G15: Imported group of properties from old ClassProperty.PropertySetName KBOB_Bauteil_HLKKSSEArchitekt. (AI) | H15: Importierte Merkmalsgruppe aus altem ClassProperty.PropertySetName KBOB_Bauteil_HLKKSSEArchitekt. (AI) | L15: Candidate | M15: 2026-06-30T12:00:00Z | N15: KBOB
D16: kbob-bauteil-hlkksse | E16: KBOB_Bauteil_HLKKSSE | F16: KBOB_Bauteil_HLKKSSE | G16: Imported group of properties from old ClassProperty.PropertySetName KBOB_Bauteil_HLKKSSE. (AI) | H16: Importierte Merkmalsgruppe aus altem ClassProperty.PropertySetName KBOB_Bauteil_HLKKSSE. (AI) | L16: Candidate | M16: 2026-06-30T12:00:00Z | N16: KBOB
D17: kbob-bauteil-architekt | E17: KBOB_Bauteil_Architekt | F17: KBOB_Bauteil_Architekt | G17: Imported group of properties from old ClassProperty.PropertySetName KBOB_Bauteil_Architekt. (AI) | H17: Importierte Merkmalsgruppe aus altem ClassProperty.PropertySetName KBOB_Bauteil_Architekt. (AI) | L17: Candidate | M17: 2026-06-30T12:00:00Z | N17: KBOB
D18: kbob-bauteil-betriebfm | E18: KBOB_Bauteil_BetriebFM | F18: KBOB_Bauteil_BetriebFM | G18: Imported group of properties from old ClassProperty.PropertySetName KBOB_Bauteil_BetriebFM. (AI) | H18: Importierte Merkmalsgruppe aus altem ClassProperty.PropertySetName KBOB_Bauteil_BetriebFM. (AI) | L18: Candidate | M18: 2026-06-30T12:00:00Z | N18: KBOB
D19: kbob-bauteil-elektroplaner | E19: KBOB_Bauteil_Elektroplaner | F19: KBOB_Bauteil_Elektroplaner | G19: Imported group of properties from old ClassProperty.PropertySetName KBOB_Bauteil_Elektroplaner. (AI) | H19: Importierte Merkmalsgruppe aus altem ClassProperty.PropertySetName KBOB_Bauteil_Elektroplaner. (AI) | L19: Candidate | M19: 2026-06-30T12:00:00Z | N19: KBOB

Sheet Data_Template
C1: GoP | E1: Properties | DM1: Documents | DS1: LOIN | DX1: Governance
C2: GoP - Designation/Bezeichnung/Désignation/Designazione | E2: Property - Designation/Bezeichnung/Désignation/Designazione | F2: GUID | G2: Grundstück ID | H2: Wirtschaftseinheit ID | I2: Ort | J2: Bezeichnung | K2: Landeskürzel | L2: Kanton | M2: Postleitzahl | N2: Politische Gemeinde | O2: GIS-Parzellennummer | P2: Grundstücksfläche | Q2: Eigentümerin | R2: Dienstbarkeiten ID | S2: Dienstbarkeitenname | T2: Gebäude ID | U2: Objekt ID | V2: Gebäudebezeichnung | W2: Objekttyp | X2: Strasse Hausnummer | Y2: Projektreferenzen | Z2: Gefährdungsstufe | AA2: Kostenträger | AB2: Objektverantwortlicher | AC2: Gebäudegrundfläche | AD2: Gebäudevolumen | AE2: Nummer Gebäudeversicherung | AF2: Baujahr | AG2: Eigentümer | AH2: Medienbezug Elektrisch | AI2: Medienbezug Wasser | AJ2: Medienbezug Heizung | AK2: Nutzungsart aussen | AL2: Gebäudeklasse | AM2: Gebäudelabel | AN2: Nachhaltigkeitsnachweis | AO2: Denkmalstatus | AP2: Erdbebenbauwerksklasse | AQ2: Schutzzone | AR2: Umgebungsfläche ID | AS2: Umgebungsflächennummer | AT2: Geschoss ID | AU2: Geschossbezeichnung | AV2: Geschossvolumen | AW2: Geschosshöhe | AX2: Geschossfläche | AY2: Aussengeschossfläche | AZ2: Beschreibung | BA2: Oberirdisch | BB2: Raum ID | BC2: Raumnummer Betrieb | BD2: Raumbezeichnung | BE2: Raum beschriftet | BF2: Raumtyp | BG2: Reinigungsgruppe | BH2: Flächenart SIA 416 | BI2: Flächenart d0165 | BJ2: Raumvolumen Netto | BK2: Nutzhöhe | BL2: Lichte Raumhöhe | BM2: Raumfläche Brutto | BN2: Raumfläche Netto | BO2: Flächenlast | BP2: Punktlast | BQ2: Personenbelegung Geplant | BR2: Personenbelegung Ist | BS2: Energiebezugsfläche | BT2: Temperatur | BU2: Fluchtweg | BV2: Fensterfläche | BW2: Fenster Öffenbar | BX2: Raumnutzer | BY2: Bodenbelag | BZ2: Deckenmaterial | CA2: Wandbelag | CB2: Luftwechselrate | CC2: Sonnenschutz | CD2: Belüftung | CE2: Klimatisiert | CF2: Luftfeuchtigkeit | CG2: Befeuchtet | CH2: Entfeuchtet | CI2: Rohrpost | CJ2: Vermietbarkeit | CK2: Bauteil ID | CL2: AKS | CM2: Antrieb | CN2: Artikelnummer | CO2: Bauteilart | CP2: Bauteiltyp | CQ2: Bauteilname | CR2: Hersteller | CS2: Produkt ID | CT2: Material | CU2: Seriennummer | CV2: Anlagenzustand | CW2: Anschaffungskosten | CX2: Brandschutzklasse | CY2: eBKP-H | CZ2: Einbruchschutzklasse | DA2: Fluchtwegfunktion | DB2: Lebensdauer | DC2: Türsteuerung | DD2: Wartungsvertrag | DE2: Wartungsintervall | DF2: Abnahmedatum | DG2: Inbetriebnahme | DH2: Nutzlast | DI2: Fensterart | DJ2: Schliessart | DK2: Doppelboden | DM2: Document - Designation/Bezeichnung/Désignation/Designazione | DN2: KBOB DK FM_i14y.csv | DS2: LOIN | DT2: LOIN_Milestone | DU2: LOIN_Role | DV2: LOIN_UseCase | DX2: Governance | DY2: Status | DZ2: Version date | EA2: Provenance (PROV)
A3: Classes
A4: Class - Designation/Bezeichnung/Désignation/Designazione | DY4: Rules.Status
A5: Grundstück | C5: KBOB_Grundstuck_Architekt | F5: x | J5: x | Q5: x | DN5: x | DT5: 31 | DU5: Architekt | DV5: Kostenplanung | DY5: Candidate | DZ5: 2026-06-30T12:00:00Z | EA5: KBOB
A6: Grundstück | G6: x | H6: x | I6: x | K6: x | L6: x | M6: x | N6: x | O6: x | P6: x | R6: x | S6: x | DN6: x | DT6: 61 | DU6: Betrieb/FM | DV6: Betrieb / Facility Management | DY6: Candidate | DZ6: 2026-06-30T12:00:00Z | EA6: KBOB
A7: Gebäude | C7: KBOB_Gebaude_Architekt | F7: x | V7: x | W7: x | DN7: x | DY7: Candidate | DZ7: 2026-06-30T12:00:00Z | EA7: KBOB
A8: Gebäude | T8: x | U8: x | X8: x | Y8: x | Z8: x | AC8: x | AD8: x | AE8: x | AF8: x | AH8: x | AI8: x | AJ8: x | AK8: x | AL8: x | AM8: x | AO8: x | AP8: x | AR8: x | AS8: x | DN8: x | DT8: 31 | DU8: Architekt | DV8: Kostenplanung | DY8: Candidate | DZ8: 2026-06-30T12:00:00Z | EA8: KBOB
A9: Gebäude | C9: KBOB_Gebaude_BetriebFM | AA9: x | AB9: x | AG9: x | AN9: x | AQ9: x | DN9: x | DT9: 61 | DU9: Betrieb/FM | DV9: Betrieb / Facility Management | DY9: Candidate | DZ9: 2026-06-30T12:00:00Z | EA9: KBOB
A10: Geschoss | C10: KBOB_Geschoss_Architekt | F10: x | AT10: x | AU10: x | DN10: x | DT10: 31 | DU10: Architekt | DV10: Kostenplanung | DY10: Candidate | DZ10: 2026-06-30T12:00:00Z | EA10: KBOB
A11: Geschoss | AV11: x | AW11: x | AX11: x | AY11: x | BA11: x | DN11: x | DT11: 31 | DU11: Architekt | DV11: Mengenermittlung | DY11: Candidate | DZ11: 2026-06-30T12:00:00Z | EA11: KBOB
A12: Geschoss | C12: KBOB_Geschoss_BetriebFM | AZ12: x | DN12: x | DT12: 61 | DU12: Betrieb/FM | DV12: Betrieb / Facility Management | DY12: Candidate | DZ12: 2026-06-30T12:00:00Z | EA12: KBOB
A13: Raum | C13: KBOB_Raum_Architekt | F13: x | AT13: x | BB13: x | BD13: x | BH13: x | BI13: x | BU13: x | BV13: x | BW13: x | CC13: x | CI13: x | DN13: x | DT13: 31 | DU13: Architekt | DV13: Kostenplanung | DY13: Candidate | DZ13: 2026-06-30T12:00:00Z | EA13: KBOB
A14: Raum | C14: KBOB_Raum_BetriebFM | BC14: x | BE14: x | BG14: x | DN14: x | DT14: 61 | DU14: Betrieb/FM | DV14: Betrieb / Facility Management | DY14: Candidate | DZ14: 2026-06-30T12:00:00Z | EA14: KBOB
A15: Raum | BF15: x | BJ15: x | BK15: x | BL15: x | BM15: x | BN15: x | BO15: x | BP15: x | BQ15: x | BR15: x | BS15: x | BT15: x | BX15: x | BY15: x | BZ15: x | CA15: x | CB15: x | CD15: x | CF15: x | CG15: x | CH15: x | CJ15: x | DN15: x | DT15: 31 | DU15: Architekt | DV15: Kostenplanung | DY15: Candidate | DZ15: 2026-06-30T12:00:00Z | EA15: KBOB
A16: Raum | C16: KBOB_Raum_HLKKSSE | CE16: x | DN16: x | DT16: 41 | DU16: HLKKSSE | DV16: Fachplanung / Energieplanung | DY16: Candidate | DZ16: 2026-06-30T12:00:00Z | EA16: KBOB
A17: Bauteil | C17: KBOB_Bauteil_HLKKSSEArchitekt | F17: x | CK17: x | CO17: x | CQ17: x | CT17: x | CY17: x | DN17: x | DT17: 41 | DU17: HLKKSSE/Architekt | DV17: Fachplanung / Energieplanung | DY17: Candidate | DZ17: 2026-06-30T12:00:00Z | EA17: KBOB
A18: Bauteil | C18: KBOB_Bauteil_HLKKSSE | AZ18: x | BB18: x | DF18: x | DH18: x | DI18: x | DJ18: x | DN18: x | DT18: 41 | DU18: HLKKSSE | DV18: Fachplanung / Energieplanung | DY18: Candidate | DZ18: 2026-06-30T12:00:00Z | EA18: KBOB
A19: Bauteil | CL19: x | CM19: x | CN19: x | CP19: x | CR19: x | CS19: x | CU19: x | DB19: x | DD19: x | DE19: x | DG19: x | DK19: x | DN19: x | DT19: 41 | DU19: HLKKSSE | DV19: Fachplanung / Energieplanung | DY19: Candidate | DZ19: 2026-06-30T12:00:00Z | EA19: KBOB
A20: Bauteil | C20: KBOB_Bauteil_Architekt | CC20: x | CX20: x | CZ20: x | DA20: x | DN20: x | DT20: 31 | DU20: Architekt | DV20: Kostenplanung | DY20: Candidate | DZ20: 2026-06-30T12:00:00Z | EA20: KBOB
A21: Bauteil | C21: KBOB_Bauteil_BetriebFM | AG21: x | CV21: x | CW21: x | DN21: x | DT21: 61 | DU21: Betrieb/FM | DV21: Betrieb / Facility Management | DY21: Candidate | DZ21: 2026-06-30T12:00:00Z | EA21: KBOB
A22: Bauteil | C22: KBOB_Bauteil_Elektroplaner | DC22: x | DN22: x | DT22: 41 | DU22: Elektroplaner | DV22: Fachplanung / Energieplanung | DY22: Candidate | DZ22: 2026-06-30T12:00:00Z | EA22: KBOB

Sheet Gelöschte Bauteile
B1: D | C1: 05 | D1: . | E1: 01 | F1: . | G1: 004 | H1: . | I1: nnn | L1: Schalldämpfer | N1: 242.2 | O1: - | P1: - | Q1: - | R1: x | U1: x | V1: Rohrzubehör | Y1: Apparat HLKS | Z1: IfcDuctSilencerType | AA1: ROUND/RECTANGULAR | AD1: 200 | AE1: 200 | AF1: 300 | AG1: 300 | AH1: 300 | AI1: 300 | AV1: x | BE1: =IF(COUNTIF(AJ1:BD1,"x")>0,"x","")
B2: D | C2: 05 | D2: . | E2: 01 | F2: . | G2: 004 | H2: . | I2: nnn | L2: Dacheinfassung | N2: 242.2 | O2: - | P2: - | Q2: - | R2: x | U2: x | V2: Rohrzubehör | Y2: Installationszubehör | Z2: IfcCoveringType | AA2: ROOFING | AD2: 200 | AE2: 200 | AF2: 300 | AG2: 300 | AH2: 300 | AI2: 300 | AV2: x | BE2: =IF(COUNTIF(AJ2:BD2,"x")>0,"x","")
B3: D | C3: 05 | D3: . | E3: 01 | F3: . | G3: 004 | H3: . | I3: nnn | L3: Revisionsstück | N3: 242.2 | O3: - | P3: - | Q3: - | R3: x | U3: x | V3: Rohrformteile | Z3: IfcPipeSegmentType | AA3: SPOOL | AD3: 200 | AE3: 200 | AF3: 300 | AG3: 300 | AH3: 300 | AI3: 300 | AV3: x | BE3: =IF(COUNTIF(AJ3:BD3,"x")>0,"x","")
B4: D | C4: 05 | D4: . | E4: 01 | F4: . | G4: 004 | H4: . | I4: nnn | L4: Messstutzen | N4: 242.2 | O4: - | P4: - | Q4: - | R4: x | U4: x | V4: Rohrformteile | Z4: IfcPipeFittingType | AA4: ENTRY | AD4: 200 | AE4: 200 | AF4: 300 | AG4: 300 | AH4: 300 | AI4: 300 | AV4: x | BE4: =IF(COUNTIF(AJ4:BD4,"x")>0,"x","")
B5: D | C5: 05 | D5: . | E5: 01 | F5: . | G5: 004 | H5: . | I5: nnn | L5: Abscheider | N5: 242.2 | O5: - | P5: - | Q5: - | R5: x | U5: x | V5: Rohrzubehör | Y5: Armatur HLKS | Z5: IfcValveType | AA5: DRAWOFFCOCK | AD5: 200 | AE5: 200 | AF5: 300 | AG5: 300 | AH5: 300 | AI5: 300 | AV5: x | BE5: =IF(COUNTIF(AJ5:BD5,"x")>0,"x","")
B6: D | C6: 05 | D6: . | E6: 01 | F6: . | G6: 004 | H6: . | I6: nnn | L6: Isolierstück | N6: 242.2 | O6: - | P6: - | Q6: - | R6: x | U6: x | V6: Rohrformteile | Z6: IfcPipeSegmentType | AA6: SPOOL | AD6: 200 | AE6: 200 | AF6: 300 | AG6: 300 | AH6: 300 | AI6: 300 | AV6: x | BE6: =IF(COUNTIF(AJ6:BD6,"x")>0,"x","")
B7: D | C7: 05 | D7: . | E7: 01 | F7: . | G7: 004 | H7: . | I7: nnn | L7: Kontrolldeckel | N7: 242.2 | O7: - | P7: - | Q7: - | R7: x | U7: x | V7: Rohrzubehör | AV7: x | BE7: =IF(COUNTIF(AJ7:BD7,"x")>0,"x","")
B8: D | C8: 05 | D8: . | E8: 01 | F8: . | G8: 004 | H8: . | I8: nnn | L8: Schlammsammler | N8: 242.2 | O8: - | P8: - | Q8: - | R8: x | U8: x | V8: Rohrzubehör | Y8: Apparat HLKS | Z8: IfcFilterType | AA8: WATERFILTER | AD8: 200 | AE8: 200 | AF8: 300 | AG8: 300 | AH8: 300 | AI8: 300 | AV8: x | BE8: =IF(COUNTIF(AJ8:BD8,"x")>0,"x","")
B9: D | C9: 05 | D9: . | E9: 01 | F9: . | G9: 004 | H9: . | I9: nnn | L9: Storzkupplung | N9: 242.2 | O9: - | P9: - | Q9: - | R9: x | U9: x | V9: Rohrformteile | Z9: IfcPipeFittingType | AA9: CONNECTOR | AD9: 200 | AE9: 200 | AF9: 300 | AG9: 300 | AH9: 300 | AI9: 300 | AV9: x | BE9: =IF(COUNTIF(AJ9:BD9,"x")>0,"x","")
B10: D | C10: 05 | D10: . | E10: 02 | F10: . | G10: 009 | H10: . | I10: nnn | L10: Wärmeübertrager | N10: 242.0 | O10: - | P10: - | Q10: - | R10: x | U10: x | V10: HLS-Bauteile | Y10: Apparat HLKS | Z10: IfcHeatExchanger | AA10: - | AD10: 200 | AE10: 200 | AF10: 300 | AG10: 300 | AH10: 300 | AI10: 300 | AV10: x | BE10: =IF(COUNTIF(AJ10:BD10,"x")>0,"x","")
B11: D | C11: 05 | D11: . | E11: 02 | F11: . | G11: 009 | H11: . | I11: nnn | L11: Wassermangelsicherung | N11: 242.2 | O11: - | P11: - | Q11: - | R11: x | U11: x | V11: HLS-Bauteile | Y11: Schaltung & Steuerung HLKSE | Z11: IfcFlowController | AA11: - | AD11: 200 | AE11: 200 | AF11: 300 | AG11: 300 | AH11: 300 | AI11: 300 | AV11: x | BE11: =IF(COUNTIF(AJ11:BD11,"x")>0,"x","")

Sheet Rules
A1: Class-Assignment | B1: Klassen-Zuordnung | C1: Affectation de classe | D1: Assegnazione della classe | E1: Property-Assignment | F1: Merkmals-Zuordnung | G1: Attribution de propriété | H1: Assegnazione della proprietà | I1: DataType | J1: IFC Data Type | K1: Status | L1: ISG - Informationssicherheitsgesetz | M1: FAIR Prinzipien | N1: LifecycleStatus
A2: Systems / Installations | B2: Systeme / Anlagen | C2: Systèmes / installations | D2: Sistemi / installazioni | E2: not defined | F2: nicht definiert | G2: non défini | H2: non definito | I2: BOOLEAN | J2: nicht definiert | K2: Preview | L2: nicht klassifiziert | M2: Zugänglich kostenpflichtig | N2: Preview
A3: Physical elements | B3: Physische Bauteile | C3: Éléments physiques | D3: Elementi fisici | E3: Identification and classification | F3: Identifikation und Klassifikation | G3: Identification et classification | H3: Identificazione e classificazione | I3: CHARACTER | J3: IfcBoolean | K3: Active | L3: intern | M3: Zugänglich unentgeltlich | N3: Active
A4: Spatial structure | B4: Räumliche Struktur | C4: Structure spatiale | D4: Struttura spaziale | E4: Manufacturer and product information | F4: Hersteller- und Produktinformationen | G4: Informations sur le fabricant et le produit | H4: Informazioni sul produttore e sul prodotto | I4: INTEGER | J4: IfcDate | K4: Inactive | L4: sensitiv | M4: Nicht zugänglich - kostenpflichtig | N4: Inactive
A5: Logical zones & groups | B5: Logische Zonen & Gruppen | C5: Zones logiques et groupes | D5: Zone logiche e gruppi | E5: Geometric characteristics | F5: Geometrische Eigenschaften | G5: Caractéristiques géométriques | H5: Caratteristiche geometriche | I5: REAL | J5: IfcDateTime | K5: Deprecated | L5: geheim | M5: Nicht zugänglich - unentgeltlich | N5: Deprecated
A6: Geometric references & grids | B6: Geometrische Referenzen & Raster | C6: Références géométriques et grilles | D6: Riferimenti geometrici e griglie | E6: Physical characteristics | F6: Physikalische Eigenschaften | G6: Caractéristiques physiques | H6: Caratteristiche fisiche | I6: STRING | J6: IfcDuration | K6: Retired | N6: Retired
A7: Actors | B7: Akteure | C7: Acteurs | D7: Attori | E7: Material and construction | F7: Material und Aufbau | G7: Matériau et constitution | H7: Materiale e struttura | I7: TIME | J7: IfcGloballyUniqueId | K7: Candidate | N7: Candidate
A8: Resources | B8: Ressourcen | C8: Ressources | D8: Risorse | E8: Operating conditions and limits | F8: Betriebsbedingungen und Grenzwerte | G8: Conditions de fonctionnement et limites | H8: Condizioni operative e limiti | I8: DATETIME | J8: IfcIdentifier | K8: Recorded | N8: Recorded
A9: Processes & tasks | B9: Prozesse & Aufgaben | C9: Processus et tâches | D9: Processi e compiti | E9: Performance characteristics | F9: Leistungs- und Funktionskennwerte | G9: Caractéristiques de performance et de fonctionnement | H9: Caratteristiche prestazionali e funzionali | J9: IfcInteger | K9: Superseded | N9: Superseded
E10: Hydraulic / flow characteristics | F10: Hydraulische / strömungstechnische Kennwerte | G10: Caractéristiques hydrauliques / d’écoulement | H10: Caratteristiche idrauliche / di flusso | J10: IfcLabel | K10: Incomplete | N10: Incomplete
E11: Thermal characteristics | F11: Thermische Kennwerte | G11: Caractéristiques thermiques | H11: Caratteristiche termiche | J11: IfcLengthMeasure
E12: Electrical characteristics | F12: Elektrische Kennwerte | G12: Caractéristiques électriques | H12: Caratteristiche elettriche | J12: IfcLocalTime
E13: Measurement, control and sensing | F13: Mess-, Steuer- und Regelungsdaten | G13: Caractéristiques de mesure, de commande et de détection | H13: Caratteristiche di misurazione, controllo e rilevamento | J13: IfcLogical
E14: Connection and interface characteristics | F14: Anschluss- und Schnittstelleninformationen | G14: Caractéristiques de raccordement et d’interface | H14: Caratteristiche di collegamento e interfaccia | J14: IfcNormalisedRatioMeasure
E15: Safety and protection characteristics | F15: Sicherheits- und Schutzmerkmale | G15: Caractéristiques de sécurité et de protection | H15: Caratteristiche di sicurezza e protezione | J15: IfcPositiveInteger
E16: Installation and delivery information | F16: Montage-, Einbau- und Lieferinformationen | G16: Informations de montage, d’installation et de livraison | H16: Informazioni di montaggio, installazione e fornitura | J16: IfcPositiveLengthMeasure
E17: Reference and documentation information | F17: Referenz- und Dokumentationsinformationen | G17: Informations de référence et de documentation | H17: Informazioni di riferimento e documentazione | J17: IfcPositiveRatioMeasure
J18: IfcPositiveTimeMeasure
J19: IfcRatioMeasure
J20: IfcReal
J21: IfcText
J22: IfcThermalTransmittanceMeasure
J23: IfcTime
J24: IfcURIReference
